{
 "mdsDat": {
 "x": [ 0.1755084, -0.1452909, 0.09655325, 0.1021909, -0.2261291, -0.07531609, 0.09236751, -0.019884 ],
"y": [ 0.1487813, 0.07823478, -0.1491224, 0.0155889, 0.1104583, -0.131239, 0.1042967, -0.1769985 ],
"topics": [ 1, 2, 3, 4, 5, 6, 7, 8 ],
"Freq": [ 12.84439, 12.66084, 12.61451, 12.58409, 12.47089, 12.37036, 12.23122,  12.2237 ],
"cluster": [        1,        1,        1,        1,        1,        1,        1,        1 ] 
},
"tinfo": {
 "Term": [ "아프다", "사람", "여성", "가족", "한국", "남자들", "바라다", "집", "잘못", "가슴", "부모", "끔찍", "소녀", "세상", "안전", "한남", "당하다", "남성", "동생", "생각", "역겹다", "타래", "이야기", "마음", "슬프다", "피해자", "남자", "글", "느끼다", "만들다", "남자들", "소녀", "당하다", "아버지", "중요", "알리다", "방", "사과", "감옥", "계정", "상황", "경험", "게시", "형제자매", "온라인", "손", "필리핀", "정의", "이름", "포함", "어려움", "강조", "맥락", "대체", "동아시아", "무력", "울리다", "종류", "소용", "따르다", "보이다", "죽다", "세상", "나오다", "존재", "괴롭히다", "가깝다", "신", "건강", "최악", "마찬가지", "인해", "끊다", "탈출", "자라다", "기록", "부모", "이유", "사람", "오후", "등장", "먹이다", "자지", "속상하다", "사이트", "포르노", "나아지다", "유죄", "공포", "가해자", "진심", "저지르다", "사회", "바래다", "트윗", "처벌", "인도", "심각", "상처", "규칙", "드리다", "링크", "권리", "사이에서", "삭제", "상관없다", "자살", "배우다", "자책", "번역", "트라우마", "청원", "화해", "정상", "가부장", "일반화", "신뢰", "아가야", "팬", "관하다", "남동생", "친구", "치료", "공개", "잘못", "잠옷", "주변", "동의", "두려워하다", "위안", "뇌", "치유", "바라다", "강하다", "방식", "학대", "아들", "응원", "후회", "차별", "친절", "불구", "생각나다", "무겁다", "범죄자", "안고", "평생", "존경", "끝나다", "인도네시아", "가슴", "타래", "아프다", "필요", "군가", "바라", "대가", "문화", "목소리", "유감", "힘들다", "비슷", "기분", "부르다", "불태우다", "어렵다", "통제", "지내다", "쓰레기", "지키다", "구성원", "주장", "살해", "한국의 여성", "터무니없다", "관심", "반응", "의자", "일주일", "터지다", "만들다", "편안", "내용", "드라마", "뜻", "의미", "몸", "은폐", "성적 학대", "신체", "빠지다", "현실", "뿌리", "글", "믿기다", "겁", "집착", "보도", "직장", "태어나다", "결혼", "세계", "끔찍", "고통", "위험성", "꺼내다", "안녕", "극복", "던지다", "들어오다", "한남", "미성년자", "작성자", "반바지", "편하다", "성기", "용기", "도와주다", "사랑", "인간", "굴욕", "잠들다", "기원", "두려움", "계속", "요청", "지치다", "형편없다", "강요", "원하다", "다르다", "불공평", "제거", "위하다", "피해자", "사촌", "공유", "강간", "먹다", "엿", "생기다", "상상", "동생", "행복", "독립", "흔하다", "괴롭힘", "일부", "저주", "참다", "아이돌", "공부", "돌리다", "최대한", "누나", "좆같다", "기억", "평화", "문제", "남자", "어머니", "엄마", "지지", "너에게", "낮잠", "혼내다", "올리다", "인연", "포식", "원래", "신고", "촬영", "성폭력", "집", "용서", "나라", "한국인", "슬프다", "지옥", "충격", "역겹다", "한국", "모습", "미치다", "마음", "선택", "전달", "죄송", "자녀", "만지다", "엄청나다", "사진", "자격", "친족성범죄", "오빠", "어리다", "남성", "가족", "떠나다", "안타깝다", "분노", "나쁘다", "스스로", "생각", "생각", "입다", "안전", "여성", "비난", "안전", "한국", "느끼다", "사건", "여성", "괜찮다", "여성", "대하다", "모르다", "남성", "집", "처음", "이야기", "형제", "가족", "의하다", "이야기", "불쌍", "일어나다", "눈물", "얘기", "방법", "일어나다", "표현", "이기다", "보내다", "자르다", "삶", "이해", "사건", "모르다", "떨어지다", "미안", "벗어나다", "마음", "딸", "행동", "대하다", "전체", "전체", "기도", "이러", "보호", "행동", "비난", "불쌍", "가족", "여동생", "그룹", "화", "텔레그램", "피해자", "미안", "역겹다", "바라다", "느끼다", "위로", "사람", "대부분", "이야기", "느끼다", "무시", "안타깝다", "오빠", "표현", "보내다", "부모", "시작", "여동생", "끔찍", "피", "자격", "형제", "슬프다", "죽이다", "무섭다", "안전", "죄송", "시작", "포옹", "잘못", "괜찮다", "나라", "일어나다", "위하다", "입다", "이야기", "사람", "안전", "문제", "괜찮다", "고통", "지옥", "공유", "오빠", "발생", "죽이다", "무섭다", "위로", "발생", "이해" ],
"logprob": [       30,       29,       28,       27,       26,       25,       24,       23,       22,       21,       20,       19,       18,       17,       16,       15,       14,       13,       12,       11,       10,        9,        8,        7,        6,        5,        4,        3,        2,        1,  -2.7515,  -3.0241,  -3.2465,   -4.374,  -4.6222,   -4.774,  -4.0097,  -4.9531,  -4.9531,  -5.1713,  -4.0891,  -3.7432,  -5.4509,  -5.4509,  -5.4509,  -5.4509,  -5.4509,   -4.774,  -5.8404,  -5.8404,  -5.8404,  -5.8404,  -5.8404,  -5.8404,  -5.8404,  -5.8404,  -5.8404,  -5.8404,  -5.8404,  -5.8404,  -3.8452,   -4.153,  -2.9736,   -4.468,  -4.7516,  -4.7516,  -4.9307,  -4.9307,  -4.9307,  -4.2474,  -5.1489,  -5.4285,  -5.4285,  -5.4285,  -5.4285,  -5.4285,  -2.8199,  -4.5998,  -2.1892,   -5.818,   -5.818,   -5.818,   -5.818,   -5.818,   -5.818,   -5.818,   -5.818,   -5.818,  -5.1489,  -4.9307,  -3.9986,  -4.2586,  -4.2586,  -4.2586,  -3.7923,  -4.9419,  -4.9419,  -5.1602,  -5.1602,  -5.1602,  -5.4398,  -5.4398,  -5.4398,  -5.4398,  -5.4398,  -5.4398,  -5.4398,  -5.4398,  -5.4398,  -4.2586,  -4.9419,  -5.8292,  -5.8292,  -5.8292,  -5.8292,  -5.8292,  -5.8292,  -5.8292,  -5.8292,  -5.8292,  -4.0343,  -4.7986,  -4.7986,  -5.1959,  -2.7131,  -5.4755,  -5.4755,  -5.4755,  -5.4755,  -5.4755,  -5.4755,  -4.6468,  -2.7336,  -4.3986,  -4.9777,  -3.7678,  -4.9777,   -5.865,   -5.865,   -5.865,   -5.865,   -5.865,   -5.865,   -5.865,   -5.865,   -5.865,   -5.865,   -5.865,   -5.865,   -5.865,  -2.8665,  -3.3928,  -2.3264,  -4.1257,  -4.2201,  -4.7243,  -4.7243,  -4.9034,  -4.9034,  -4.0394,  -4.1257,  -4.4408,  -5.4012,  -5.4012,  -5.4012,  -5.4012,  -5.4012,  -4.1257,  -4.3244,  -4.9034,  -5.7907,  -5.7907,  -5.7907,  -5.7907,  -5.7907,  -5.7907,  -5.7907,  -5.7907,  -5.7907,  -5.7907,  -3.7518,  -4.2582,  -4.6582,  -4.6582,  -4.6582,  -4.6582,  -4.8372,  -4.8372,  -4.8372,  -5.0555,  -5.0555,  -5.0555,  -5.0555,  -3.4172,  -5.3351,  -5.3351,  -5.3351,  -5.3351,  -5.3351,  -5.3351,  -5.3351,  -4.0595,  -2.7264,  -3.7518,  -5.7245,  -5.7245,  -5.7245,  -5.7245,  -5.7245,  -5.7245,  -3.2243,   -4.432,  -4.8946,  -5.1129,  -5.1129,  -5.1129,  -5.1129,  -5.1129,  -4.2113,   -4.432,  -5.3925,  -5.3925,  -5.3925,  -5.7819,  -5.7819,  -5.7819,  -5.7819,  -5.7819,  -5.7819,  -5.7819,  -5.7819,  -5.7819,  -5.7819,  -3.8092,  -3.4746,  -5.1129,  -3.9512,  -5.3925,  -5.3925,  -5.3925,  -3.8424,  -3.9109,  -3.2575,  -4.7488,  -4.9278,  -4.9278,  -5.1461,  -5.1461,  -5.1461,  -5.4257,  -5.4257,  -5.4257,  -5.4257,  -5.4257,  -5.4257,  -5.4257,   -4.597,  -4.1501,  -3.9109,  -3.3342,  -4.3488,  -4.9278,  -4.9278,  -4.9278,  -5.8151,  -5.8151,  -5.8151,  -5.8151,  -5.8151,  -5.8151,  -4.9419,  -4.2586,  -4.5151,  -2.8078,  -4.6111,  -4.1137,  -4.6468,  -3.2951,  -4.1642,    -3.96,  -3.2951,  -2.6485,  -5.1602,  -3.9607,   -3.437,  -5.1216,  -5.1216,  -4.0307,  -5.1602,  -5.1602,  -5.1959,   -4.597,  -3.9109,  -4.8372,   -3.664,  -4.9777,  -3.4172,  -2.6716,  -4.7488,   -4.468,  -4.7629,  -4.6468,  -4.7488,  -3.6215,  -3.5705,  -4.2944,  -3.0954,  -2.6571,  -4.2113,  -3.1881,   -3.055,  -3.8281,  -4.2944,  -2.8205,  -4.5151,  -2.8663,  -4.2474,   -4.468,  -3.6215,  -3.4247,  -5.0555,   -3.533,   -4.468,  -2.9309,  -5.1216,  -3.5231,   -4.774,  -3.9873,  -5.4285,  -5.4012,  -5.3351,  -3.9512,   -4.774,  -5.3351,  -4.5638,  -5.4509,  -4.9034,  -4.5064,  -4.2586,  -4.5064,  -5.3925,  -4.2586,  -4.7488,  -4.0667,  -4.6111,  -4.7516,  -4.2586,  -4.9034,  -4.9531,  -5.1713,  -5.1713,  -4.7516,  -4.6468,  -4.6222,  -4.9034,  -3.3342,  -4.9531,  -4.9419,  -4.9278,  -4.9777,  -4.4904,  -4.4652,  -4.1642,  -3.9109,  -4.2474,  -4.9777,  -3.7678,  -4.9278,  -4.0667,  -4.2582,  -5.1129,  -4.9034,  -4.3746,  -4.8372,  -4.9531,  -4.3244,  -4.9419,  -4.9777,   -4.432,  -5.1461,  -4.7516,  -4.7629,  -4.5064,  -5.0555,  -4.9278,   -4.468,  -4.7629,  -5.0555,  -5.1959,  -4.6111,  -5.1489,  -5.1713,  -4.9777,  -5.1713,  -4.9419,  -4.9777,  -5.0555,  -4.9278,  -5.4509,  -5.4509,  -5.1489,  -5.1489,  -5.1959,  -5.4012,  -5.4012,  -5.4012,  -5.3925,  -5.3925,  -5.1461,  -5.1461 ],
"loglift": [       30,       29,       28,       27,       26,       25,       24,       23,       22,       21,       20,       19,       18,       17,       16,       15,       14,       13,       12,       11,       10,        9,        8,        7,        6,        5,        4,        3,        2,        1,   2.0371,   2.0324,   2.0275,   1.9777,   1.9577,    1.943,   1.9304,   1.9229,   1.9229,   1.8937,   1.8538,   1.8505,   1.8475,   1.8475,   1.8475,   1.8475,   1.8475,   1.8033,    1.763,    1.763,    1.763,    1.763,    1.763,    1.763,    1.763,    1.763,    1.763,    1.763,    1.763,    1.763,   2.0215,   2.0057,   1.9972,    1.984,   1.9583,   1.9583,   1.9384,   1.9384,   1.9384,   1.9125,   1.9094,   1.8636,   1.8636,   1.8636,   1.8636,   1.8636,   1.8572,   1.8558,   1.7917,   1.7797,   1.7797,   1.7797,   1.7797,   1.7797,   1.7797,   1.7797,   1.7797,   1.7797,   1.7199,   1.6554,   2.0175,   2.0024,   2.0024,   2.0024,    1.969,     1.94,     1.94,   1.9106,   1.9106,   1.9106,   1.8641,   1.8641,   1.8641,   1.8641,   1.8641,   1.8641,   1.8641,   1.8641,   1.8641,   1.8236,   1.7801,   1.7791,   1.7791,   1.7791,   1.7791,   1.7791,   1.7791,   1.7791,   1.7791,   1.7791,   2.0177,    1.958,    1.958,   1.9065,   1.8666,   1.8583,   1.8583,   1.8583,   1.8583,   1.8583,   1.8583,   1.8482,   1.8007,   1.7938,   1.7722,    1.771,    1.771,   1.7703,   1.7703,   1.7703,   1.7703,   1.7703,   1.7703,   1.7703,   1.7703,   1.7703,   1.7703,   1.7703,   1.7703,   1.7703,   2.0643,   2.0524,   2.0257,   2.0216,   2.0158,   1.9748,   1.9748,   1.9552,   1.9552,   1.9468,   1.9423,   1.8935,   1.8812,   1.8812,   1.8812,   1.8812,   1.8812,   1.8651,    1.825,   1.8052,   1.7983,   1.7983,   1.7983,   1.7983,   1.7983,   1.7983,   1.7983,   1.7983,   1.7983,   1.7983,   2.0481,   2.0215,   1.9895,   1.9895,   1.9895,   1.9895,    1.971,    1.971,    1.971,    1.944,    1.944,    1.944,    1.944,   1.9053,   1.9011,   1.9011,   1.9011,   1.9011,   1.9011,   1.9011,   1.9011,   1.8872,   1.8416,   1.8356,   1.8224,   1.8224,   1.8224,   1.8224,   1.8224,   1.8224,   2.0758,   2.0187,   1.9731,   1.9442,   1.9442,   1.9442,   1.9442,   1.9442,   1.9399,   1.9111,   1.8984,   1.8984,   1.8984,   1.8146,   1.8146,   1.8146,   1.8146,   1.8146,   1.8146,   1.8146,   1.8146,   1.8146,   1.8146,    1.783,   1.7586,   1.7565,   1.7524,   1.6716,   1.6716,   1.6666,   2.0549,   2.0517,   2.0385,   1.9896,    1.969,    1.969,   1.9391,   1.9391,   1.9391,   1.8918,   1.8918,   1.8918,   1.8918,   1.8918,   1.8918,   1.8918,   1.8807,   1.8776,   1.8633,   1.8552,   1.8389,   1.8136,   1.8136,    1.808,   1.8055,   1.8055,   1.8055,   1.8055,   1.8055,   1.8055,   1.7787,   1.7656,   1.7689,   1.6348,   1.7425,   1.7312,   1.7366,   1.7364,   1.7128,   1.7242,    1.669,   1.5074,   1.7282,    1.611,   1.6056,   1.7479,   1.7415,   1.5625,   1.7191,   1.7065,   1.6965,   1.6737,   1.5634,   1.6935,   1.4564,   1.6372,   1.4469,   1.2589,   1.6181,   1.5296,    1.579,   1.5453,   1.6052,    1.346,   1.3969,   1.4356,   1.2398,   1.0536,    1.437,   1.1472,   1.1009,   1.2254,   1.3298,   0.8903,   1.3797,   0.8444,   1.3057,   1.3669,   1.2426,    1.018,   1.6215,   1.0262,   1.3461,   0.9996,   1.5811,   1.0361,   1.3835,   1.1264,   1.6407,   1.6561,   1.6788,   1.1625,   1.3582,   1.6764,   1.3605,   1.6099,   1.4363,   1.3393,   1.3656,   1.3286,   1.6499,   1.3525,   1.5928,   0.9759,   1.4794,    1.277,   1.2944,   1.3418,   1.2922,   1.4008,   1.3935,    1.255,   1.3818,   1.0261,   1.2541,   0.5963,   1.1476,    1.519,   1.5434,   1.4976,   0.7427,   1.1459,      0.8,   0.6235,   0.8061,   1.3938,   0.2131,   1.4093,   0.4925,   0.7953,   1.3479,   1.0942,   0.7458,    1.295,   0.9712,   0.3527,   1.3806,   1.1229,    0.136,   1.4462,   0.7226,   1.0513,   0.5252,   1.3609,   1.0245,  -0.1328,   0.8303,    1.267,   1.1645,  -0.0314,   0.7459,   0.6736,    0.136,   0.4208,   0.7881,  -0.4185,  -1.0746,  -0.5926,   0.3233,   0.4439,   0.4384,   0.7281,   0.5077,  -0.2809,   1.1831,   1.0151,   0.5599,    0.979,   1.4383,   0.6996 ],
"Freq": [      245,      356,      466,      374,      298,      158,      204,      224,      195,      137,      177,      197,      121,      132,      249,       95,       97,      147,       95,      132,      133,       82,      199,      123,      124,      101,      106,       93,      121,       57, 156.3699, 119.0582,  95.3144, 30.86694,   24.083, 20.69103, 44.43483, 17.29905, 17.29905, 13.90708, 41.04285, 58.00271, 10.51511, 10.51511, 10.51511, 10.51511, 10.51511, 20.69103,  7.12314,  7.12314,  7.12314,  7.12314,  7.12314,  7.12314,  7.12314,  7.12314,  7.12314,  7.12314,  7.12314,  7.12314, 51.63072, 37.95371,  123.435, 27.69595, 20.85744, 20.85744, 17.43819, 17.43819, 17.43819, 34.53445, 14.01894, 10.59968, 10.59968, 10.59968, 10.59968, 10.59968, 143.9505, 24.27669, 270.4629, 7.180431, 7.180431, 7.180431, 7.180431, 7.180431, 7.180431, 7.180431, 7.180431, 7.180431, 14.01894, 17.43819,  44.1284, 34.02266, 34.02266, 34.02266, 54.23414, 17.17976, 17.17976, 13.81118, 13.81118, 13.81118,  10.4426,  10.4426,  10.4426,  10.4426,  10.4426,  10.4426,  10.4426,  10.4426,  10.4426, 34.02266, 17.17976, 7.074018, 7.074018, 7.074018, 7.074018, 7.074018, 7.074018, 7.074018, 7.074018, 7.074018, 42.47566, 19.77874, 19.77874, 13.29391, 159.2027, 10.05149, 10.05149, 10.05149, 10.05149, 10.05149, 10.05149, 23.02116, 155.9603, 29.50599, 16.53633, 55.44533, 16.53633, 6.809076, 6.809076, 6.809076, 6.809076, 6.809076, 6.809076, 6.809076, 6.809076, 6.809076, 6.809076, 6.809076, 6.809076, 6.809076, 135.3279, 79.95073, 232.2378, 38.41788, 34.95681, 21.11253, 21.11253, 17.65146, 17.65146, 41.87896, 38.41788, 28.03467, 10.72932, 10.72932, 10.72932, 10.72932, 10.72932, 38.41788, 31.49574, 17.65146, 7.268249, 7.268249, 7.268249, 7.268249, 7.268249, 7.268249, 7.268249, 7.268249, 7.268249, 7.268249,  55.3872, 33.37904, 22.37496, 22.37496, 22.37496, 22.37496, 18.70693, 18.70693, 18.70693, 15.03891, 15.03891, 15.03891, 15.03891, 77.39536, 11.37088, 11.37088, 11.37088, 11.37088, 11.37088, 11.37088, 11.37088, 40.71509, 154.4239,  55.3872, 7.702855, 7.702855, 7.702855, 7.702855, 7.702855, 7.702855,  92.8027, 27.73808, 17.46472, 14.04026, 14.04026, 14.04026, 14.04026, 14.04026, 34.58698, 27.73808, 10.61581, 10.61581, 10.61581, 7.191353, 7.191353, 7.191353, 7.191353, 7.191353, 7.191353, 7.191353, 7.191353, 7.191353, 7.191353, 51.70925, 72.25598, 14.04026, 44.86035, 10.61581, 10.61581, 10.61581, 49.98964, 46.67906,  89.7165, 20.19449, 16.88392, 16.88392, 13.57334, 13.57334, 13.57334, 10.26277, 10.26277, 10.26277, 10.26277, 10.26277, 10.26277, 10.26277, 23.50506, 36.74735, 46.67906, 83.09536,  30.1262, 16.88392, 16.88392, 16.88392, 6.952201, 6.952201, 6.952201, 6.952201, 6.952201, 6.952201, 17.17976, 34.02266, 26.26358, 140.7451, 23.91692, 39.23324, 23.02116, 86.40593, 37.39124, 45.34003, 86.40593, 173.3297, 13.81118, 45.71808, 76.48966, 14.19039, 14.19039, 41.43589, 13.81118, 13.81118, 13.29391, 23.50506, 46.67906, 18.70693, 61.88847, 16.53633, 77.39536, 161.2918, 20.19449, 27.69595, 20.54834, 23.02116, 20.19449, 64.33988, 66.39128, 32.74841, 107.6393, 168.7659, 34.58698, 96.22716,  109.925, 52.20291, 32.74841, 142.9906, 26.26358,   139.41, 34.53445, 27.69595, 64.33988, 78.14225, 15.03891,  71.5706, 27.69595, 128.3429, 14.19039, 68.83152, 20.69103, 44.79221, 10.59968, 10.72932, 11.37088, 44.86035, 20.69103, 11.37088, 24.31362, 10.51511, 17.65146, 26.04299, 34.02266, 26.04299, 10.61581, 34.02266, 20.19449, 41.37296, 23.91692, 20.85744, 34.02266, 17.65146, 17.29905, 13.90708, 13.90708, 20.85744, 23.02116,   24.083, 17.65146, 83.09536, 17.29905, 17.17976, 16.88392, 16.53633, 27.47497, 26.81563, 37.39124, 46.67906, 34.53445, 16.53633, 55.44533, 16.88392, 41.37296, 33.37904, 14.04026, 17.65146, 29.71101, 18.70693, 17.29905, 31.49574, 17.17976, 16.53633, 27.73808, 13.57334, 20.85744, 20.54834, 26.04299, 15.03891, 16.88392, 27.69595, 20.54834, 15.03891, 13.29391, 23.91692, 14.01894, 13.90708, 16.53633, 13.90708, 17.17976, 16.53633, 15.03891, 16.88392, 10.51511, 10.51511, 14.01894, 14.01894, 13.29391, 10.72932, 10.72932, 10.72932, 10.61581, 10.61581, 13.57334, 13.57334 ],
"Total": [      245,      356,      466,      374,      298,      158,      204,      224,      195,      137,      177,      197,      121,      132,      249,       95,       97,      147,       95,      132,      133,       82,      199,      123,      124,      101,      106,       93,      121,       57, 158.7593, 121.4476, 97.70383, 33.25638, 26.47243, 23.08046, 50.19284, 19.68849, 19.68849, 16.29652, 50.05343, 70.97062, 12.90455, 12.90455, 12.90455, 12.90455, 12.90455, 26.54153, 9.512577, 9.512577, 9.512577, 9.512577, 9.512577, 9.512577, 9.512577, 9.512577, 9.512577, 9.512577, 9.512577, 9.512577, 54.01743, 40.34041, 132.3066, 30.08266, 23.24415, 23.24415,  19.8249,  19.8249,  19.8249, 40.28974, 16.40565, 12.98639, 12.98639, 12.98639, 12.98639, 12.98639, 177.4869, 29.97398, 356.0479,  9.56714,  9.56714,  9.56714,  9.56714,  9.56714,  9.56714,  9.56714,  9.56714,  9.56714,  19.8301, 26.30973, 46.52017, 36.41443, 36.41443, 36.41443, 60.01789, 19.57153, 19.57153, 16.20295, 16.20295, 16.20295, 12.83437, 12.83437, 12.83437, 12.83437, 12.83437, 12.83437, 12.83437, 12.83437, 12.83437, 43.54353, 22.96351, 9.465794, 9.465794, 9.465794, 9.465794, 9.465794, 9.465794, 9.465794, 9.465794, 9.465794, 44.88005, 22.18314, 22.18314,  15.6983, 195.6391, 12.45589, 12.45589, 12.45589, 12.45589, 12.45589, 12.45589, 28.81752, 204.7127, 38.99767, 22.33269, 74.97009, 22.35997, 9.213468, 9.213468, 9.213468, 9.213468, 9.213468, 9.213468, 9.213468, 9.213468, 9.213468, 9.213468, 9.213468, 9.213468, 9.213468, 137.7104, 82.33326, 245.6245, 40.80041, 37.33934, 23.49506, 23.49506, 20.03399, 20.03399, 47.92951, 44.16899, 33.84165, 13.11185, 13.11185, 13.11185, 13.11185, 13.11185, 47.71086, 40.71678,  23.2764, 9.650776, 9.650776, 9.650776, 9.650776, 9.650776, 9.650776, 9.650776, 9.650776, 9.650776, 9.650776, 57.74903, 35.74087, 24.73679, 24.73679, 24.73679, 24.73679, 21.06877, 21.06877, 21.06877, 17.40074, 17.40074, 17.40074, 17.40074, 93.08182, 13.73271, 13.73271, 13.73271, 13.73271, 13.73271, 13.73271, 13.73271, 49.86087,  197.942, 71.42604, 10.06469, 10.06469, 10.06469, 10.06469, 10.06469, 10.06469, 95.18889, 30.12427,  19.8509, 16.42645, 16.42645, 16.42645, 16.42645, 16.42645,  40.6412, 33.54352,   13.002,   13.002,   13.002, 9.577542, 9.577542, 9.577542, 9.577542, 9.577542, 9.577542, 9.577542, 9.577542, 9.577542, 9.577542, 71.08258, 101.7779, 19.81842, 63.58478, 16.31257, 16.31257, 16.39397, 52.38721, 49.07664, 95.57515, 22.59207, 19.28149, 19.28149, 15.97092, 15.97092, 15.97092, 12.66035, 12.66035, 12.66035, 12.66035, 12.66035, 12.66035, 12.66035, 29.32189, 45.98343, 59.25256, 106.3292, 39.18545, 22.52391, 22.52391, 22.65007, 9.349778, 9.349778, 9.349778, 9.349778, 9.349778, 9.349778, 22.99599, 46.14169, 35.59011, 224.3685, 33.19422, 55.20552, 32.21859, 124.5151, 53.46003, 64.82922, 133.1939, 298.8774, 19.44537, 72.54428, 123.1456, 19.81533,  19.9415, 71.01216, 19.62221, 19.87098, 19.36633, 36.06425, 79.97537, 27.80593, 113.9343, 25.56186, 147.2213, 374.4483, 32.75662, 47.38801, 33.58674, 39.00949, 33.18223, 132.7561, 132.7561, 61.92742, 249.8134, 466.4945, 67.20181, 249.8134, 298.8774, 121.8121,  68.8386, 466.4945, 52.52089, 466.4945, 73.91753, 55.75884, 147.2213, 224.3685, 24.02188, 199.6922, 56.92852, 374.4483, 23.41142, 199.6922, 40.38582, 114.6928, 16.22881, 16.42242, 17.15197, 114.6928, 41.42059, 17.19378, 50.99572, 16.36562, 33.66033, 55.16289,  68.8386, 55.75884, 16.67002, 69.74792, 33.59615, 123.1456,  43.1876, 45.94107, 73.91753, 36.99384, 36.99384, 26.67973, 26.87499, 46.96348, 45.94107, 67.20181, 40.38582, 374.4483, 42.74948, 29.81655, 29.51197, 29.39269, 101.7779, 69.74792, 133.1939, 204.7127, 121.8121, 32.60605, 356.0479, 33.74664, 199.6922, 121.8121, 29.82173, 47.38801, 113.9343, 41.42059, 50.99572, 177.4869, 34.24364, 42.74948,  197.942, 26.14684, 79.97537, 56.92852, 124.5151, 31.17592, 49.58168, 249.8134, 71.01216, 34.24364,  32.9667, 195.6391, 52.52089, 55.20552, 114.6928, 71.08258, 61.92742, 199.6922, 356.0479, 249.8134, 59.25256, 52.52089, 71.42604, 53.46003, 63.58478, 113.9343, 26.35413, 31.17592, 49.58168, 32.60605, 26.35413, 55.16289 ],
"Category": [ "Default", "Default", "Default", "Default", "Default", "Default", "Default", "Default", "Default", "Default", "Default", "Default", "Default", "Default", "Default", "Default", "Default", "Default", "Default", "Default", "Default", "Default", "Default", "Default", "Default", "Default", "Default", "Default", "Default", "Default", "Topic1", "Topic1", "Topic1", "Topic1", "Topic1", "Topic1", "Topic1", "Topic1", "Topic1", "Topic1", "Topic1", "Topic1", "Topic1", "Topic1", "Topic1", "Topic1", "Topic1", "Topic1", "Topic1", "Topic1", "Topic1", "Topic1", "Topic1", "Topic1", "Topic1", "Topic1", "Topic1", "Topic1", "Topic1", "Topic1", "Topic2", "Topic2", "Topic2", "Topic2", "Topic2", "Topic2", "Topic2", "Topic2", "Topic2", "Topic2", "Topic2", "Topic2", "Topic2", "Topic2", "Topic2", "Topic2", "Topic2", "Topic2", "Topic2", "Topic2", "Topic2", "Topic2", "Topic2", "Topic2", "Topic2", "Topic2", "Topic2", "Topic2", "Topic2", "Topic2", "Topic3", "Topic3", "Topic3", "Topic3", "Topic3", "Topic3", "Topic3", "Topic3", "Topic3", "Topic3", "Topic3", "Topic3", "Topic3", "Topic3", "Topic3", "Topic3", "Topic3", "Topic3", "Topic3", "Topic3", "Topic3", "Topic3", "Topic3", "Topic3", "Topic3", "Topic3", "Topic3", "Topic3", "Topic3", "Topic3", "Topic4", "Topic4", "Topic4", "Topic4", "Topic4", "Topic4", "Topic4", "Topic4", "Topic4", "Topic4", "Topic4", "Topic4", "Topic4", "Topic4", "Topic4", "Topic4", "Topic4", "Topic4", "Topic4", "Topic4", "Topic4", "Topic4", "Topic4", "Topic4", "Topic4", "Topic4", "Topic4", "Topic4", "Topic4", "Topic4", "Topic5", "Topic5", "Topic5", "Topic5", "Topic5", "Topic5", "Topic5", "Topic5", "Topic5", "Topic5", "Topic5", "Topic5", "Topic5", "Topic5", "Topic5", "Topic5", "Topic5", "Topic5", "Topic5", "Topic5", "Topic5", "Topic5", "Topic5", "Topic5", "Topic5", "Topic5", "Topic5", "Topic5", "Topic5", "Topic5", "Topic6", "Topic6", "Topic6", "Topic6", "Topic6", "Topic6", "Topic6", "Topic6", "Topic6", "Topic6", "Topic6", "Topic6", "Topic6", "Topic6", "Topic6", "Topic6", "Topic6", "Topic6", "Topic6", "Topic6", "Topic6", "Topic6", "Topic6", "Topic6", "Topic6", "Topic6", "Topic6", "Topic6", "Topic6", "Topic6", "Topic7", "Topic7", "Topic7", "Topic7", "Topic7", "Topic7", "Topic7", "Topic7", "Topic7", "Topic7", "Topic7", "Topic7", "Topic7", "Topic7", "Topic7", "Topic7", "Topic7", "Topic7", "Topic7", "Topic7", "Topic7", "Topic7", "Topic7", "Topic7", "Topic7", "Topic7", "Topic7", "Topic7", "Topic7", "Topic7", "Topic8", "Topic8", "Topic8", "Topic8", "Topic8", "Topic8", "Topic8", "Topic8", "Topic8", "Topic8", "Topic8", "Topic8", "Topic8", "Topic8", "Topic8", "Topic8", "Topic8", "Topic8", "Topic8", "Topic8", "Topic8", "Topic8", "Topic8", "Topic8", "Topic8", "Topic8", "Topic8", "Topic8", "Topic8", "Topic8", "Topic3", "Topic3", "Topic4", "Topic7", "Topic3", "Topic4", "Topic4", "Topic8", "Topic3", "Topic5", "Topic8", "Topic1", "Topic3", "Topic4", "Topic5", "Topic5", "Topic5", "Topic7", "Topic3", "Topic3", "Topic4", "Topic8", "Topic8", "Topic6", "Topic2", "Topic4", "Topic6", "Topic7", "Topic8", "Topic2", "Topic3", "Topic4", "Topic8", "Topic3", "Topic6", "Topic4", "Topic5", "Topic3", "Topic7", "Topic7", "Topic7", "Topic4", "Topic4", "Topic4", "Topic4", "Topic1", "Topic2", "Topic2", "Topic3", "Topic4", "Topic6", "Topic1", "Topic2", "Topic3", "Topic5", "Topic7", "Topic1", "Topic2", "Topic2", "Topic5", "Topic6", "Topic7", "Topic1", "Topic6", "Topic7", "Topic1", "Topic5", "Topic6", "Topic3", "Topic6", "Topic7", "Topic3", "Topic8", "Topic2", "Topic3", "Topic2", "Topic3", "Topic5", "Topic1", "Topic1", "Topic1", "Topic2", "Topic4", "Topic1", "Topic5", "Topic8", "Topic1", "Topic3", "Topic8", "Topic4", "Topic1", "Topic8", "Topic3", "Topic8", "Topic2", "Topic4", "Topic4", "Topic8", "Topic2", "Topic6", "Topic7", "Topic5", "Topic6", "Topic6", "Topic1", "Topic5", "Topic3", "Topic4", "Topic7", "Topic8", "Topic2", "Topic3", "Topic6", "Topic6", "Topic8", "Topic2", "Topic3", "Topic6", "Topic4", "Topic3", "Topic2", "Topic1", "Topic4", "Topic1", "Topic3", "Topic4", "Topic6", "Topic8", "Topic1", "Topic1", "Topic2", "Topic2", "Topic4", "Topic5", "Topic5", "Topic5", "Topic7", "Topic7", "Topic8", "Topic8" ] 
},
"token.table": {
 "Term": [ "가깝다", "가부장", "가슴", "가족", "가족", "가족", "가해자", "가해자", "감옥", "강간", "강간", "강요", "강조", "강하다", "강하다", "강하다", "건강", "겁", "게시", "결혼", "경험", "경험", "경험", "계속", "계정", "고통", "고통", "공개", "공부", "공유", "공유", "공유", "공포", "공포", "관심", "관하다", "괜찮다", "괜찮다", "괜찮다", "괴롭히다", "괴롭힘", "구성원", "군가", "굴욕", "권리", "규칙", "그룹", "그룹", "그룹", "극복", "글", "글", "글", "글", "기도", "기도", "기록", "기분", "기억", "기억", "기원", "꺼내다", "끊다", "끔찍", "끔찍", "끔찍", "끔찍", "끝나다", "나라", "나라", "나쁘다", "나쁘다", "나쁘다", "나아지다", "나오다", "남동생", "남성", "남성", "남성", "남자", "남자", "남자", "남자", "남자들", "낮잠", "내용", "너에게", "너에게", "뇌", "누나", "눈물", "눈물", "느끼다", "느끼다", "느끼다", "다르다", "당하다", "대가", "대부분", "대부분", "대부분", "대체", "대하다", "대하다", "대하다", "던지다", "도와주다", "독립", "돌리다", "동생", "동생", "동아시아", "동의", "두려움", "두려워하다", "드라마", "드리다", "들어오다", "등장", "따르다", "딸", "딸", "딸", "떠나다", "떠나다", "떠나다", "떨어지다", "떨어지다", "뜻", "링크", "마음", "마음", "마음", "마찬가지", "만들다", "만지다", "만지다", "맥락", "먹다", "먹다", "먹이다", "모르다", "모르다", "모습", "모습", "목소리", "몸", "무겁다", "무력", "무섭다", "무섭다", "무섭다", "무섭다", "무섭다", "무시", "무시", "무시", "문제", "문제", "문화", "미성년자", "미안", "미안", "미안", "미치다", "미치다", "미치다", "미치다", "미치다", "믿기다", "바라", "바라다", "바라다", "바래다", "반바지", "반응", "발생", "발생", "방", "방", "방법", "방법", "방식", "방식", "배우다", "번역", "번역", "번역", "범죄자", "벗어나다", "벗어나다", "보내다", "보내다", "보내다", "보도", "보이다", "보호", "보호", "보호", "보호", "부르다", "부모", "부모", "분노", "분노", "분노", "불공평", "불구", "불쌍", "불쌍", "불태우다", "비난", "비난", "비난", "비슷", "비슷", "빠지다", "뿌리", "사건", "사건", "사과", "사람", "사람", "사람", "사람", "사람", "사랑", "사랑", "사이에서", "사이트", "사진", "사진", "사진", "사촌", "사촌", "사회", "삭제", "살해", "삶", "삶", "삶", "상관없다", "상상", "상처", "상황", "상황", "생각", "생각", "생각나다", "생기다", "선택", "선택", "성기", "성적 학대", "성폭력", "성폭력", "세계", "세계", "세상", "세상", "소녀", "소용", "속상하다", "손", "스스로", "스스로", "스스로", "슬프다", "슬프다", "슬프다", "슬프다", "슬프다", "시작", "시작", "신", "신고", "신고", "신뢰", "신체", "심각", "쓰레기", "쓰레기", "아가야", "아들", "아들", "아버지", "아이돌", "아프다", "아프다", "안고", "안녕", "안전", "안전", "안전", "안전", "안타깝다", "안타깝다", "알리다", "얘기", "얘기", "어려움", "어렵다", "어리다", "어리다", "어머니", "어머니", "어머니", "엄마", "엄마", "엄청나다", "엄청나다", "여동생", "여동생", "여동생", "여성", "여성", "여성", "여성", "여성", "역겹다", "역겹다", "역겹다", "엿", "엿", "오빠", "오빠", "오빠", "오빠", "오후", "온라인", "올리다", "요청", "용기", "용서", "용서", "용서", "울리다", "원래", "원하다", "위로", "위로", "위로", "위안", "위하다", "위하다", "위하다", "위험성", "유감", "유감", "유죄", "은폐", "응원", "의미", "의자", "의하다", "의하다", "이기다", "이기다", "이러", "이러", "이러", "이름", "이야기", "이야기", "이야기", "이야기", "이유", "이유", "이해", "이해", "이해", "이해", "인간", "인간", "인도", "인도네시아", "인연", "인해", "일반화", "일부", "일어나다", "일어나다", "일어나다", "일어나다", "일주일", "입다", "입다", "입다", "자격", "자격", "자격", "자녀", "자녀", "자라다", "자르다", "자르다", "자살", "자지", "자책", "작성자", "잘못", "잘못", "잘못", "잘못", "잠들다", "잠옷", "저주", "저지르다", "전달", "전달", "전체", "전체", "정상", "정의", "정의", "제거", "존경", "존재", "종류", "좆같다", "죄송", "죄송", "죄송", "죄송", "주변", "주장", "죽다", "죽이다", "죽이다", "죽이다", "중요", "지내다", "지내다", "지내다", "지옥", "지옥", "지지", "지지", "지치다", "지키다", "지키다", "직장", "진심", "집", "집", "집", "집착", "차별", "참다", "처벌", "처음", "처음", "청원", "촬영", "촬영", "최대한", "최악", "최악", "충격", "충격", "충격", "치료", "치유", "치유", "친구", "친절", "친족성범죄", "친족성범죄", "타래", "탈출", "태어나다", "터무니없다", "터지다", "텔레그램", "텔레그램", "텔레그램", "통제", "트라우마", "트라우마", "트윗", "트윗", "팬", "편안", "편하다", "평생", "평화", "평화", "포르노", "포식", "포옹", "포옹", "포옹", "포옹", "포함", "표현", "표현", "피", "피", "피해자", "피해자", "필리핀", "필요", "학대", "학대", "학대", "한국", "한국", "한국", "한국", "한국의 여성", "한국인", "한국인", "한국인", "한남", "행동", "행동", "행복", "현실", "형제", "형제", "형제", "형제", "형제자매", "형편없다", "혼내다", "화", "화", "화", "화해", "후회", "흔하다", "힘들다", "힘들다" ],
"Topic": [ 2, 3, 5, 3, 7, 8, 2, 4, 1, 7, 8, 7, 1, 2, 4, 6, 2, 6, 1, 6, 1, 4, 6, 7, 1, 2, 6, 4, 8, 3, 4, 7, 2, 7, 5, 3, 1, 2, 4, 2, 8, 5, 5, 7, 3, 3, 1, 3, 5, 6, 4, 5, 6, 8, 1, 5, 2, 5, 2, 8, 7, 6, 2, 2, 5, 6, 7, 4, 1, 4, 4, 7, 8, 2, 2, 4, 3, 5, 6, 2, 4, 6, 8, 1, 8, 6, 3, 8, 4, 8, 2, 4, 2, 4, 6, 7, 1, 5, 5, 6, 8, 1, 2, 3, 8, 6, 7, 8, 8, 5, 8, 1, 4, 7, 4, 6, 3, 6, 2, 1, 2, 3, 8, 4, 5, 8, 6, 7, 6, 3, 2, 4, 5, 2, 6, 3, 6, 1, 7, 8, 2, 2, 6, 3, 4, 5, 6, 4, 1, 2, 4, 5, 7, 8, 4, 6, 7, 1, 8, 5, 7, 3, 7, 8, 1, 4, 5, 6, 8, 6, 5, 4, 8, 3, 7, 5, 5, 8, 1, 3, 2, 6, 1, 4, 3, 3, 5, 6, 4, 6, 8, 1, 6, 7, 6, 2, 1, 2, 3, 5, 5, 2, 5, 3, 6, 8, 7, 4, 1, 5, 5, 1, 4, 7, 5, 7, 6, 6, 3, 4, 1, 1, 2, 4, 6, 8, 6, 7, 3, 2, 3, 7, 8, 1, 7, 3, 3, 5, 2, 3, 5, 3, 8, 3, 1, 8, 3, 6, 4, 8, 4, 5, 7, 6, 4, 5, 1, 6, 2, 4, 1, 1, 2, 1, 5, 6, 8, 3, 4, 6, 7, 8, 3, 6, 2, 3, 7, 3, 6, 3, 2, 5, 3, 2, 4, 1, 8, 5, 6, 4, 6, 2, 5, 7, 8, 2, 5, 1, 5, 8, 1, 5, 4, 8, 2, 4, 8, 4, 8, 4, 6, 1, 4, 7, 1, 3, 4, 6, 8, 3, 6, 8, 1, 7, 2, 5, 6, 8, 2, 1, 8, 7, 7, 3, 5, 7, 1, 8, 7, 1, 4, 7, 4, 1, 2, 7, 6, 5, 6, 2, 6, 4, 6, 5, 2, 5, 5, 6, 1, 4, 6, 1, 1, 2, 4, 7, 2, 8, 4, 6, 7, 8, 2, 7, 3, 4, 8, 2, 3, 8, 1, 2, 4, 7, 5, 3, 4, 8, 2, 5, 8, 2, 3, 2, 1, 5, 3, 2, 3, 7, 1, 3, 4, 6, 7, 4, 8, 3, 3, 5, 1, 5, 3, 1, 5, 7, 4, 2, 1, 8, 3, 6, 7, 8, 4, 5, 2, 1, 5, 6, 1, 4, 5, 6, 2, 3, 4, 8, 7, 4, 5, 6, 3, 2, 4, 7, 6, 4, 8, 3, 6, 8, 3, 3, 4, 8, 2, 3, 2, 5, 7, 4, 1, 4, 4, 4, 3, 6, 5, 2, 6, 5, 5, 1, 4, 6, 5, 1, 3, 1, 3, 3, 6, 7, 4, 2, 8, 2, 8, 1, 4, 6, 7, 1, 1, 6, 1, 8, 1, 7, 1, 5, 3, 4, 5, 1, 2, 3, 7, 5, 3, 4, 7, 7, 2, 4, 8, 6, 1, 2, 3, 4, 1, 7, 8, 1, 2, 8, 3, 4, 8, 3, 5 ],
"Freq": [ 0.8575076, 0.7395048, 0.9803182, 0.3418362, 0.4299659, 0.2216594, 0.6461487, 0.2660612, 0.8634486, 0.6743267, 0.2452097, 0.7308764, 0.7358679, 0.1025702, 0.7692768, 0.1025702, 0.8575076, 0.801007, 0.8524126, 0.801007, 0.8172396, 0.05636135, 0.1127227, 0.7308764, 0.8590791, 0.1960069, 0.7700273, 0.828115, 0.7898676, 0.06290813, 0.2044514, 0.7077165, 0.7059975, 0.2017136, 0.7253303, 0.7395048, 0.2094405, 0.2665606, 0.4950411, 0.9034531, 0.8765931, 0.7253303, 0.9373491, 0.8460239, 0.7791576,  0.86404, 0.234769, 0.5701532, 0.1341537, 0.7948583, 0.04297295, 0.04297295, 0.8272292, 0.07520266, 0.5247429, 0.412298, 0.8470405, 0.838936, 0.1364169, 0.8185011, 0.8460239, 0.7948583, 0.8470405, 0.03536389, 0.03536389, 0.7780056, 0.1414556, 0.7597573, 0.2535978, 0.7064511, 0.5896002, 0.2819827, 0.1025392, 0.7316711, 0.9307689, 0.9358277, 0.4347198, 0.02716999, 0.5230222, 0.1034523, 0.03761903, 0.07523806, 0.7805949, 0.9826195, 0.7486809, 0.8893635, 0.1765999, 0.7505494, 0.8028334, 0.7898676, 0.677807, 0.2464753, 0.2873278, 0.4268871, 0.2709091, 0.7308764, 0.9723262, 0.893805, 0.1185303, 0.3259583, 0.5037538, 0.7358679, 0.4735006, 0.4599721, 0.05411436, 0.7948583, 0.852284, 0.8816744, 0.7898676, 0.04185188, 0.9416674, 0.7358679, 0.8028334, 0.7308764, 0.8028334, 0.8893635, 0.7791576, 0.7948583, 0.7316711, 0.7358679, 0.2547028, 0.5557151, 0.1620836, 0.1221127, 0.2136972, 0.6105635, 0.2399517, 0.6598671, 0.8893635, 0.7791576, 0.3329391, 0.03248186, 0.6171554, 0.8533648, 0.952397, 0.704545, 0.2012986, 0.7358679, 0.6743267, 0.2452097, 0.7316711, 0.5021625, 0.4662938, 0.7199657, 0.2057045, 0.8984731, 0.9018089, 0.7597573, 0.7358679, 0.1411812, 0.2016874, 0.08067495, 0.2218561, 0.3428686, 0.335326, 0.1341304, 0.4694564, 0.185646, 0.7932147, 0.8984731, 0.9294832, 0.4874697, 0.1003614, 0.3871083, 0.05513874, 0.6340955, 0.1516315, 0.1102775, 0.05513874, 0.801007, 0.893805, 0.7620438, 0.2295901, 0.9336957, 0.852284, 0.7253303, 0.4173918, 0.5312259, 0.876619, 0.07969264, 0.2332094, 0.6413259, 0.1791096, 0.7612159, 0.7791576, 0.7808278, 0.09186209, 0.09186209, 0.7597573, 0.3274185, 0.5953064, 0.3333613, 0.1568759, 0.4706277, 0.801007, 0.9626523, 0.149052, 0.4471559, 0.2981039, 0.08517256, 0.838936, 0.8113276, 0.1746608, 0.6252468, 0.2381892, 0.1190946, 0.7308764, 0.7597573, 0.5199845, 0.445701, 0.838936, 0.3571333, 0.1041639, 0.5208193, 0.8273827, 0.1181975, 0.8620323, 0.8620323, 0.4939089, 0.4793822, 0.8634486, 0.01966028, 0.758325, 0.1544736, 0.04212917, 0.01966028, 0.09842229, 0.861195, 0.7791576, 0.7316711, 0.194098, 0.1109132, 0.6654789, 0.2018324, 0.7064135, 0.9336957, 0.7791576, 0.7253303, 0.3267942, 0.1188343, 0.5347542, 0.7791576, 0.9576857,  0.86404, 0.8191246, 0.1398505, 0.482087, 0.4971522, 0.7597573, 0.9544314, 0.2018639, 0.7065235, 0.852284, 0.9018089,  0.73054, 0.1966838, 0.1403907, 0.8222881, 0.9296591, 0.05290743, 0.9798462, 0.7358679, 0.7316711, 0.8524126, 0.2109563, 0.1205464, 0.6027322, 0.03212461, 0.03212461, 0.2088099, 0.03212461, 0.6906791, 0.4964426, 0.4380375, 0.8575076, 0.7392594, 0.1739434, 0.7395048, 0.8620323,  0.86404, 0.1719193, 0.7613569, 0.7395048, 0.1788911, 0.7602872, 0.9321521, 0.7898676, 0.9445314, 0.04478381, 0.7597573, 0.7948583, 0.1120837, 0.4323227, 0.3842868, 0.06805079, 0.5908668, 0.3798429, 0.9098604, 0.6698161, 0.2435695, 0.7358679, 0.838936, 0.6650533, 0.2738455, 0.1020787, 0.1020787, 0.7655903, 0.1775891, 0.7547535, 0.6712682, 0.2065441, 0.3976656, 0.3976656, 0.1637447, 0.297967, 0.3622765, 0.3065416, 0.008574591, 0.02143648, 0.2777904, 0.06006279, 0.645675, 0.2439922, 0.6709785, 0.5441732, 0.09654685, 0.2633096, 0.08776986, 0.7316711, 0.8524126, 0.7486809, 0.7308764, 0.852284, 0.7230175, 0.1205029, 0.1205029, 0.7358679, 0.7486809, 0.7308764, 0.1226766, 0.5213756, 0.3373607, 0.8028334, 0.196954, 0.05627258, 0.7315435, 0.7948583, 0.8762869, 0.08345589, 0.7316711, 0.9018089, 0.7597573, 0.8893635, 0.7253303, 0.2989993, 0.5979987, 0.2326422, 0.6397661, 0.5209304, 0.1488373, 0.2976745, 0.7358679, 0.3605548, 0.205316, 0.085131, 0.3455317, 0.8006946, 0.1334491, 0.07251252, 0.4713314, 0.1994094, 0.2537938, 0.1192481, 0.8347365, 0.8686084, 0.7597573, 0.7486809, 0.8470405, 0.7395048, 0.8765931, 0.06103258, 0.3923523, 0.148222, 0.3923523, 0.7253303, 0.2745149, 0.5328819, 0.1614794, 0.2625808, 0.1375423, 0.5876809, 0.2038507, 0.7134773, 0.8470405, 0.6721408, 0.2444148, 0.7791576, 0.7316711, 0.7791576, 0.8563842, 0.03578017, 0.1226749, 0.812721, 0.02044581, 0.8460239, 0.8028334, 0.8765931, 0.9336957, 0.2005867, 0.7020536, 0.4595359, 0.4865674, 0.7395048, 0.7912128, 0.1507072, 0.7308764, 0.7597573, 0.9034531, 0.7358679, 0.7898676, 0.295724, 0.05632838, 0.5773659, 0.05632838, 0.8028334, 0.7253303, 0.9419834, 0.1283041, 0.3528364, 0.4811405, 0.9066034, 0.08383836, 0.7964644, 0.08383836, 0.2618779, 0.6921059, 0.1775891, 0.7547535, 0.7308764, 0.1718478, 0.7733153, 0.801007, 0.9458262, 0.01782781, 0.3476424, 0.6284304, 0.801007, 0.7597573, 0.7898676, 0.8686084, 0.6244306, 0.291401, 0.7395048, 0.7368608, 0.2167238, 0.7898676, 0.8687075, 0.09928085, 0.1696766, 0.6941314, 0.107976, 0.9015858, 0.1388044, 0.7981255, 0.9015858, 0.7597573, 0.2517449, 0.6833076, 0.9716608, 0.8470405, 0.801007, 0.7253303, 0.7253303, 0.2381545, 0.5783751, 0.1360883, 0.838936, 0.1741894, 0.7403051, 0.0666468, 0.8997318, 0.7395048, 0.9233127, 0.852284, 0.7597573, 0.1522287, 0.8046376, 0.7316711, 0.7486809, 0.3336701, 0.3943374, 0.1213346, 0.1213346, 0.7358679, 0.5069942, 0.458709, 0.420701, 0.5354376, 0.2652834, 0.7074225, 0.8524126, 0.9313631, 0.09337056, 0.7336259, 0.1467252, 0.5788327, 0.02342098, 0.02342098, 0.3680439, 0.7253303, 0.1241519, 0.7138736, 0.1241519, 0.9770048, 0.4571073, 0.5006414, 0.8852665, 0.8620323, 0.07026355, 0.4918448, 0.3688836, 0.07026355, 0.8524126, 0.7308764, 0.7486809, 0.1355382, 0.2371919, 0.5760374, 0.7395048, 0.7597573, 0.8816744, 0.09056127, 0.8603321 ] 
},
"R":       30,
"lambda.step":     0.01,
"plot.opts": {
 "xlab": "PC1",
"ylab": "PC2" 
},
"topic.order": [ 5, 7, 4, 1, 8, 6, 3, 2 ] 
}