{
 "mdsDat": {
 "x": [ -0.2057709, -0.1649453, -0.01552527, -0.2029145, 0.07751224, 0.08117991, -0.1126285, 0.1919182, 0.08753142, 0.1739202, 0.08972248 ],
"y": [ -0.0690051, -0.03375554, -0.04869591, -0.01199074, -0.09497658, -0.1785999, 0.1753771, -0.1011817, -0.01364947, 0.06522409, 0.3112537 ],
"topics": [ 1, 2, 3, 4, 5, 6, 7, 8, 9, 10, 11 ],
"Freq": [ 14.38427, 13.92725, 12.58365, 10.99327, 10.70359, 9.289083, 8.741444,   8.3059, 4.393181, 4.120446, 2.557918 ],
"cluster": [        1,        1,        1,        1,        1,        1,        1,        1,        1,        1,        1 ] 
},
"tinfo": {
 "Term": [ "돈", "잃다", "빚", "갚다", "친구", "처벌", "끊다", "사이트", "신고", "불법", "부모", "중독", "조사", "도박", "경찰서", "청소년", "경찰", "전화", "출석", "게임", "토토", "계좌", "고등학생", "연락", "사기", "문자", "생각", "따다", "학교", "바카라", "치료", "목표", "증상", "센터", "다리", "슬프다", "팟", "저축", "단도박", "날다", "머릿속", "악순환", "팁", "저금", "치료법", "의지", "립니", "실천", "딜러", "일지", "피폐", "약물", "유로", "상담", "끊다", "마이너스", "상위", "스케일", "빛다", "제주도", "용기", "하루하루", "뛰어내리다", "장사", "거금", "빚", "감당", "독촉", "꺼내다", "눈물", "각서", "작업대출", "깨다", "집안", "일주일", "삼촌", "배달", "쪽지", "주만", "수학여행", "유도", "말씀", "돈맛", "덜다", "여건", "엄두", "이실직고", "목숨", "견디다", "정신과", "상대방", "차용증", "목걸이", "돌려주다", "민사", "녹음", "연", "캡쳐", "갈취", "채무", "소송", "재촉", "사채", "메신저", "방관", "주인", "강요", "주작", "상환", "의무", "불법원인급여", "아버님", "형", "자진", "기한", "추심", "대여금", "도벽", "전말", "의도", "파워", "볼", "방금", "수중", "비상금", "경기", "여름", "사다리", "꽁머니", "자전거", "대순가", "도요", "불", "하키", "짜증", "욕심", "분하다", "결심", "부리다", "종목", "아이패드", "행운", "맛", "떨어지다", "네임드", "불행", "맛있다", "실력", "맴", "초심자", "대리", "정지", "인증", "송금", "뱅크", "라이브스코어", "홍보", "디스코드", "유출", "작업", "직원", "전화번호", "총판", "페메", "포상금", "코드", "승인", "비번", "그램", "꽁", "계좌번호", "대포", "당첨", "페이스북", "추천인", "페북", "톡", "누르다", "국민은행", "더치트", "적발", "자수", "입출", "단속", "입출금", "박처", "공소시효", "지장", "형벌", "개정", "수위", "횟수", "궁금증", "집행유예", "조취", "유학", "구글", "입금액", "오락", "잡히다", "벌금", "억대", "출금액", "자동", "닝", "뉴스", "강하다", "판정", "합", "처벌", "담배", "놀다", "피다", "일진", "우울증", "오빠", "헤어지다", "사귀다", "전학", "양아치", "술", "이사", "신", "남친", "새끼", "운동", "키", "때리다", "조카", "애기", "수학", "담", "노다", "초등학교", "신경", "관계", "검정고시", "패다", "자식", "밉다", "인천", "대상자", "보호자", "수사관", "이메일", "수사", "조율", "휴대", "피싱", "출석", "진술서", "홈페이지", "대구", "관할", "이용자", "검찰청", "참석", "장소", "이수", "경찰관", "경위", "즉심", "모시다", "충청북도", "사이버", "종결", "서울", "지방", "조치", "지참", "금융", "제공", "등기", "위원회", "경력", "신원", "사회봉사", "마진", "공무원", "보유", "동의서", "일탈", "교사", "감독원", "정시", "불리", "마이스터", "모양", "신한은행", "억", "적히다", "취업", "군인", "봉사", "사행성", "취직", "기부", "됀", "일자", "강남", "재판", "소년", "보호관찰", "보호", "판매", "명령", "송치", "오토바이", "면허", "환불", "변제", "장터", "피해자", "행각", "특수", "서류", "공판", "청법", "기소", "딥", "페이크", "이탈", "점유", "교도소", "유치장", "변재", "상품권", "서부", "구입", "디지털", "아이템", "포커", "메이플", "한국", "스포츠토토", "도박장", "오버", "피파", "세금", "워치", "선수", "복", "코인", "그림장", "룰렛", "현질", "화면", "훈계", "부스타", "코", "탭", "잼", "빗", "마작", "자필", "택배", "비고", "수련", "고르다", "양주", "중독", "꾸다", "멘탈", "심정", "충동", "광고", "차단", "걸리다", "훈방", "거래", "담보", "메꾸다", "몸", "합리", "포인트", "상습", "선도", "선임", "공갈", "번개", "털어놓다", "할머니", "자살", "드리다", "손해", "초범", "출금", "초등학생", "영장", "지다", "급하다", "증거", "방학", "서버", "적용", "요번", "죽다", "빚다", "이자", "가입", "영향", "여자", "무리", "지내다", "정보", "최종", "차리다", "협박", "원금", "그래프", "우편", "경찰서", "갚다", "부모", "공짜", "금액", "누나", "범죄", "생각나다", "다행", "환전", "프로그램", "문자", "법원", "잃다", "아들", "신고", "복구", "회원", "이름", "조사", "사기", "절제", "계좌", "웃다", "확인", "유예", "부산", "게임", "빌리다", "배팅", "사이트", "입금", "과거", "동의", "합의", "친구", "잃다", "만원", "방", "불법", "용돈", "수업", "전화", "처분", "자금", "이득", "속", "만중", "교육", "수사대", "팀", "따다", "얘기", "고소", "번호", "사용", "마약", "바카라", "구하다", "겁나다", "경찰", "꿈", "도박", "벌리다", "돈", "충전", "넣다", "싫다", "요구", "사기죄", "시작", "권유", "주다", "가능", "앱", "청소년", "스트레스", "조회", "사건", "중학생", "엄마", "갚다", "따다", "접다", "토토로", "성격", "정신", "힘들다", "금", "남다", "삭제", "미성년자", "공부", "연락", "실형", "컴퓨터", "처음", "손", "진학", "지금", "사이트", "카카오톡", "사고", "예정", "소년원", "화투", "선물", "고등학생", "대출", "생각", "신고", "반성", "경찰", "기록", "활동", "방법", "생각", "조언", "내용", "날짜", "시작", "계정", "보내다", "가족", "듣다", "통보", "돈", "돈", "쉬다", "통지서", "주식", "수익", "사설", "아빠", "기소유예", "내역", "방법", "좋다", "아빠", "인스타", "기록", "조사", "변호사", "학교폭력", "복구", "도박", "남자", "돈", "용돈", "사람", "도박", "울산", "폭행", "불법", "친구", "엄마", "청소년", "고등학생", "선생님", "휴대폰", "도박", "입금", "치다", "번호", "인정", "나이", "호기심", "걸다", "온라인", "만들다", "학교", "고등학생", "빌리다", "마음", "토토", "남", "청소년", "학교", "상황", "기간", "후회", "통장", "하루", "토토", "온라인", "사실", "달다", "중학교", "도움", "조언", "사람", "다니다", "도박", "탈퇴", "작년", "형사", "상태", "살다", "보이스피싱", "토토", "걱정", "후회", "연락", "많다", "도박", "패", "모르다", "불법", "중독", "생각", "많다", "부탁", "고등학생", "가정", "친구", "전화", "좋다", "작년", "재미있다", "벌다", "사기", "토토", "배", "문제", "좋다", "이익", "은행", "치다", "섯다", "전문", "친구", "주다", "부모", "도박", "남", "돈", "내역", "남다", "부모", "해결", "경찰서", "고등학교", "토토", "처음", "고등학생", "도박", "살다", "연락", "생각", "상황", "문자", "중학생", "고등학교", "경찰", "공부", "욕", "도박", "고등학생", "처음", "청소년", "결과", "끊다", "불법", "처벌", "청소년", "중학생", "인생", "물다", "핸드폰", "팀", "후반", "부탁", "문제", "조사", "학교", "금액", "처벌", "연락", "반성", "공부", "계좌", "친구", "불법", "중학생", "친구", "상황", "고등학생", "경찰", "벌다", "학교", "친구", "고등학생", "사실", "중학생", "친구", "필요", "저녁", "지역", "인생", "계좌", "온라인", "손", "얘기", "처벌", "고소", "시작", "사이트", "손", "부모", "죽다", "중학생", "토토", "모르다", "사이트", "진행", "찾다", "부모", "도박", "걸리다", "잃다", "지금", "나오다", "모르다", "온라인", "사람", "좋다", "성인", "고등학생", "먹다", "도박", "부모", "모르다", "사용", "사용", "미성년자", "사람", "엄마", "먹다", "사람", "통장", "고등학생", "경찰서" ],
"logprob": [       30,       29,       28,       27,       26,       25,       24,       23,       22,       21,       20,       19,       18,       17,       16,       15,       14,       13,       12,       11,       10,        9,        8,        7,        6,        5,        4,        3,        2,        1,  -4.7044,  -6.9332,  -7.1319,  -5.0347,  -7.2483,    -7.38,    -7.38,  -6.7675,  -5.7538,  -7.5318,  -6.7675,  -7.7109,  -7.7109,  -7.7109,  -7.7109,  -6.4442,  -7.1319,  -7.9291,  -7.9291,  -7.9291,  -7.9291,  -7.9291,    -7.38,   -4.309,  -2.9232,  -6.9332,  -8.2087,  -8.2087,  -8.2087,  -8.2087,  -5.9053,  -6.4282,  -6.7926,   -6.909,  -7.0407,  -2.6222,  -5.9516,  -7.1926,  -7.1926,  -6.5076,  -7.3716,  -7.3716,  -7.3716,  -5.7013,  -7.5899,  -7.5899,  -7.5899,  -7.5899,  -7.5899,  -7.5899,  -7.5899,  -3.9697,  -7.8694,  -7.8694,  -7.8694,  -7.8694,  -7.8694,  -7.8694,  -7.8694,  -7.8694,  -5.6861,  -6.3071,  -6.3071,  -6.4492,  -6.1259,  -6.8136,  -6.8136,  -6.0721,    -6.93,    -6.93,  -5.7223,  -7.0617,  -7.0617,  -7.2135,  -7.2135,  -7.2135,  -6.7093,  -7.3926,  -7.3926,  -7.3926,  -7.3926,  -7.3926,  -3.9842,  -5.9263,  -7.0617,  -7.6108,  -7.6108,  -7.6108,  -7.6108,  -7.6108,  -5.7857,  -6.0725,  -7.0595,  -7.1638,  -7.1638,  -5.9032,  -6.2764,  -5.0666,  -5.8725,  -7.4119,  -7.4119,  -7.4119,  -7.4119,  -7.4119,  -6.6573,  -5.6085,  -7.5637,  -7.5637,  -7.5637,  -7.5637,  -7.5637,  -7.5637,  -6.1898,  -6.8788,  -7.7428,  -7.7428,  -7.7428,  -7.7428,  -7.7428,  -7.7428,  -4.4687,  -4.9098,  -5.2093,  -5.4635,  -5.8514,  -6.0048,  -6.3281,  -5.2605,     -5.9,  -6.5881,  -6.5881,     -5.9,  -5.8514,  -6.6924,  -6.6924,  -6.6924,  -6.6924,  -6.6924,  -6.6924,  -6.8088,  -5.7185,  -6.9406,  -6.9406,  -5.7185,  -7.0924,  -7.0924,  -7.0924,  -7.0924,  -7.0924,  -7.0924,  -5.1069,  -4.3524,  -6.1917,  -7.0692,  -4.1459,  -7.2499,  -7.2499,  -6.4668,  -6.6665,  -7.6023,  -4.8079,  -7.1555,  -7.7541,  -7.7541,  -7.9332,  -7.9332,  -7.9332,  -6.4226,  -7.4705,  -6.2629,  -4.6941,  -8.1514,  -8.1514,  -8.1514,  -8.1514,  -8.1514,  -8.1514,  -8.1514,  -6.9898,   -2.725,  -4.3759,  -4.6458,  -5.4084,  -5.9291,  -6.0618,   -5.446,  -6.2148,  -6.2148,  -6.2148,   -6.301,  -5.0677,  -6.4997,  -6.4997,  -6.4997,  -6.6161,  -5.9291,  -6.7479,  -6.7479,  -6.7479,  -6.8997,  -6.8997,  -6.8997,  -6.3954,  -6.3954,  -6.2148,  -5.3722,  -7.0787,  -7.0787,  -7.0787,  -7.0787,  -5.1698,  -6.0953,  -5.3411,  -6.1638,  -6.2374,  -4.1362,  -6.6017,  -6.6017,  -6.6017,  -3.4963,  -5.6278,  -6.7181,  -6.1638,  -6.8499,  -6.8499,  -6.8499,  -6.8499,  -6.8499,  -6.8499,  -5.3105,  -7.0017,  -7.0017,  -7.0017,  -7.0017,  -4.8008,  -6.6017,  -5.5105,  -6.3168,  -4.5319,  -7.1808,  -3.9924,  -3.9924,  -5.2675,  -4.5996,  -5.9561,  -6.0506,  -6.2712,  -6.2712,  -4.9586,   -6.403,  -6.5548,  -6.7338,  -6.7338,  -6.7338,  -6.7338,  -6.9521,  -6.9521,  -6.9521,  -6.9521,  -6.9521,  -6.5548,  -5.0273,  -6.1548,  -6.0506,  -5.8699,   -6.403,  -5.3624,  -6.5548,  -6.0506,  -7.2317,  -3.8435,  -4.1676,  -4.8264,  -5.3139,   -5.168,  -6.0553,  -5.2143,  -5.3677,  -6.1717,  -5.5489,  -6.3035,  -6.3035,  -4.4328,  -6.4553,  -6.4553,  -6.4553,  -6.6343,  -6.6343,  -6.6343,  -6.6343,  -6.6343,  -6.6343,  -6.6343,  -6.8526,  -6.8526,  -6.8526,  -6.8526,  -6.8526,  -6.8526,  -6.8526,  -5.0371,  -5.2869,  -5.6205,  -5.6205,  -4.2417,  -5.3604,  -5.9729,  -5.9729,  -5.9729,  -6.1248,  -6.1248,  -6.1248,  -6.1248,  -6.1248,  -5.4398,  -5.4398,  -5.8412,  -6.3038,  -6.3038,  -6.3038,  -6.3038,  -6.5221,  -6.5221,  -6.5221,  -6.5221,  -6.5221,  -6.5221,  -6.5221,  -6.5221,  -6.5221,  -3.3286,  -7.0276,  -6.2003,  -6.4282,  -6.9651,  -5.4318,  -5.6011,  -4.2536,  -4.4143,  -3.9551,  -5.6174,    -7.38,  -6.5932,  -6.8788,  -6.6924,  -5.4664,  -4.0443,  -5.6174,   -5.691,  -6.4553,  -6.7926,  -6.5939,  -5.5636,  -4.4149,  -5.4382,  -4.7994,   -4.997,  -5.9933,  -5.8566,  -5.9053,    -6.93,  -5.3557,  -5.5856,  -6.3281,  -7.2499,  -6.9332,  -4.0303,  -6.3547,  -4.6386,  -4.1123,  -6.3395,  -5.0418,   -6.301,  -5.9933,  -3.7569,  -5.8566,   -5.368,  -4.8009,  -5.0687,  -6.1917,  -5.4055,  -3.2528,  -3.0844,   -2.743,   -6.186,  -3.9237,  -5.8121,  -4.1031,  -5.6488,  -6.3228,  -4.7719,  -5.9709,  -3.7156,   -5.168,  -2.8508,  -5.4426,  -3.3447,  -4.4226,  -5.2093,  -4.8735,  -3.2841,  -3.4669,  -6.5613,  -3.3949,  -6.1354,  -4.6496,  -6.1548,  -4.4642,    -3.12,   -4.709,    -4.94,  -3.1603,  -4.1503,  -5.7905,  -6.1548,  -4.7947,  -2.2871,  -2.7333,  -5.3449,  -5.3425,   -3.194,  -4.5031,  -6.0618,  -3.4389,  -4.5476,  -5.7599,  -5.5856,  -6.0725,  -6.2629,  -5.4742,  -5.9141,  -5.5871,  -4.1578,  -4.9093,  -5.4082,  -4.2269,  -4.3689,  -4.9278,  -3.5879,   -6.222,   -6.909,  -3.6844,  -5.0636,  -2.0753,  -7.0407,  -2.3185,  -4.4734,  -4.6983,  -4.4161,  -4.7308,   -4.764,  -4.1085,  -5.6241,  -4.2674,  -4.6139,     -5.9,  -3.2725,  -5.5258,  -5.1012,  -4.3495,  -3.8103,  -4.3459,  -3.4531,   -4.034,  -5.4382,   -5.656,  -5.8121,  -5.0347,  -4.7509,  -6.1259,  -4.6438,  -5.6011,  -4.6638,   -4.276,  -3.4343,  -6.3035,  -5.4398,   -4.309,  -4.5808,  -5.9561,  -4.7644,  -3.4196,  -4.9867,  -5.0166,  -5.4742,  -4.8264,  -6.1248,  -6.1248,  -3.2802,  -5.9053,  -3.5487,  -3.5969,   -5.257,  -3.5112,  -4.9259,  -6.1248,  -4.5271,  -3.8426,  -5.1046,  -5.3305,  -5.9726,   -4.034,  -4.9285,  -5.0699,  -5.0677,  -5.2084,  -5.7905,  -2.8958,  -2.6553,  -5.7583,  -5.7905,  -5.3604,  -5.7059,   -4.997,  -4.2182,  -5.5871,  -4.0713,  -4.5453,  -4.4149,  -4.7653,  -5.7185,  -5.6891,  -4.2148,   -4.764,  -4.8928,  -5.0902,  -2.5971,  -4.9444,  -2.9992,   -4.635,  -4.1636,  -2.3976,  -5.2869,  -6.1827,  -3.6019,  -2.7519,  -4.0919,  -3.9878,  -3.3556,  -4.7495,  -4.4335,  -2.7245,  -4.4568,  -4.9444,  -4.4779,  -5.4245,  -5.3606,  -5.1304,  -4.4958,  -4.8392,  -5.3272,  -4.1426,  -3.7676,   -5.088,    -5.04,  -3.7821,  -5.3722,  -3.5162,  -3.8511,  -5.0477,  -5.2983,  -5.0726,  -4.4293,  -5.4668,  -4.1192,  -4.5645,  -4.4099,  -5.6511,  -5.2084,  -5.5093,  -5.2373,    -4.73,  -5.0166,    -2.99,  -5.1142,   -4.917,   -4.859,  -4.4328,  -4.5475,  -5.6278,  -4.1548,  -4.9444,  -5.3872,  -4.5434,  -4.8492,  -2.7985,  -5.9729,  -4.8561,  -4.3296,  -4.4015,  -3.9113,   -4.612,  -5.1339,   -3.319,  -5.4847,  -3.8883,  -4.4109,    -4.35,  -4.8008,  -5.3604,   -5.094,  -4.8559,  -3.8402,  -5.0371,  -5.1485,  -4.6438,  -5.4134,  -5.1012,  -4.7947,  -5.8412,  -5.7248,  -4.0264,  -4.6226,  -3.9417,  -2.9377,  -5.0371,  -3.4886,   -4.896,   -4.623,  -4.3696,  -5.6301,  -4.6788,  -5.0166,  -4.6207,   -4.956,  -4.0437,  -3.2727,   -5.192,  -4.5119,  -4.6429,  -5.2354,  -4.7719,  -4.3247,  -4.8636,  -4.2839,    -5.04,  -5.4084,  -3.2325,  -4.4358,  -4.7659,  -4.6052,  -5.3604,  -4.4961,  -4.2343,  -4.2188,    -4.73,  -4.7947,  -5.0418,  -5.2807,  -5.3604,  -5.4398,  -5.6205,  -5.3305,  -4.8942,  -4.5235,  -4.6335,  -4.6773,  -4.9426,  -4.6945,  -5.2233,  -4.8838,   -4.697,  -4.4015,  -4.6341,  -4.9947,  -4.3044,  -4.8264,  -4.2188,  -4.5476,   -5.368,  -5.2129,  -4.3045,  -4.4222,  -5.1698,  -4.7174,  -4.3723,  -5.2869,  -5.6205,  -5.6205,  -5.2433,   -4.896,  -5.0011,   -5.278,  -5.2391,  -4.8008,   -5.168,  -5.1276,   -4.905,   -5.151,  -4.7742,  -5.2953,  -4.8559,  -5.2354,  -5.0418,  -4.9577,  -5.5261,  -5.4398,   -4.952,  -4.6458,  -5.1402,  -5.1276,  -5.2116,  -5.4398,  -5.0068,  -5.2869,  -5.1217,   -5.278,  -5.6173,  -5.0235,  -5.2084,   -5.094,  -5.4082,  -5.2273,  -5.1142,   -5.168,  -5.5846,  -5.4398,  -5.1809,  -5.5261,  -5.1809,  -5.4426,  -5.2084,  -5.1809 ],
"loglift": [       30,       29,       28,       27,       26,       25,       24,       23,       22,       21,       20,       19,       18,       17,       16,       15,       14,       13,       12,       11,       10,        9,        8,        7,        6,        5,        4,        3,        2,        1,   1.8784,   1.8571,     1.84,   1.8305,   1.8284,   1.8137,   1.8137,    1.813,    1.812,   1.7946,   1.7769,   1.7686,   1.7686,   1.7686,   1.7686,   1.7637,   1.7322,   1.7311,   1.7311,   1.7311,   1.7311,   1.7311,   1.7177,   1.7122,   1.6903,   1.6764,   1.6723,   1.6723,   1.6723,   1.6723,   1.9414,   1.9214,   1.9002,   1.8918,   1.8811,   1.8741,   1.8701,    1.867,    1.867,   1.8504,   1.8478,   1.8478,   1.8478,   1.8347,   1.8198,   1.8198,   1.8198,   1.8198,   1.8198,   1.8198,   1.8198,   1.8004,   1.7755,   1.7755,   1.7755,   1.7755,   1.7755,   1.7755,   1.7755,   1.7755,   2.0457,    2.023,    2.023,   2.0156,   1.9947,   1.9914,   1.9914,    1.986,   1.9818,   1.9818,   1.9746,   1.9697,   1.9697,   1.9537,   1.9537,   1.9537,    1.939,    1.932,    1.932,    1.932,    1.932,    1.932,   1.9284,   1.9183,   1.9165,   1.9004,   1.9004,   1.9004,   1.9004,   1.9004,   2.1721,   2.1605,   2.0855,   2.0729,   2.0729,   2.0683,   2.0606,   2.0429,   2.0414,   2.0379,   2.0379,   2.0379,   2.0379,   2.0379,     2.03,   2.0175,   2.0126,   2.0126,   2.0126,   2.0126,   2.0126,   2.0126,   2.0068,   2.0056,   1.9784,   1.9784,   1.9784,   1.9784,   1.9784,   1.9784,    2.225,   2.2198,   2.2147,    2.209,    2.197,    2.191,   2.1748,   2.1628,   2.1622,   2.1577,   2.1577,   2.1554,   2.1528,   2.1496,   2.1496,   2.1496,   2.1496,   2.1496,   2.1496,   2.1396,   2.1356,   2.1269,   2.1269,   2.1156,   2.1103,   2.1103,   2.1103,   2.1103,   2.1103,   2.1103,   2.3542,   2.3484,   2.3122,   2.2286,   2.2268,   2.2018,   2.2018,   2.1802,   2.1695,   2.1363,   2.1274,    2.112,   2.1019,   2.1019,   2.0559,   2.0559,   2.0559,    2.048,   2.0295,   2.0249,   2.0064,   1.9912,   1.9912,   1.9912,   1.9912,   1.9912,   1.9912,   1.9912,   1.9789,   1.9779,   2.4264,   2.4231,   2.4074,   2.3876,   2.3808,   2.3794,   2.3718,   2.3718,   2.3718,   2.3661,   2.3566,   2.3512,   2.3512,   2.3512,   2.3411,   2.3372,   2.3283,   2.3283,   2.3283,   2.3115,   2.3115,   2.3115,   2.3028,   2.2964,    2.291,   2.2903,   2.2886,   2.2886,   2.2886,   2.2886,   2.4631,   2.4261,   2.4221,   2.4218,   2.4169,   2.3984,   2.3871,   2.3871,   2.3871,   2.3828,   2.3827,   2.3753,   2.3665,   2.3604,   2.3604,   2.3604,   2.3604,   2.3604,   2.3604,   2.3448,   2.3409,   2.3409,   2.3409,   2.3409,    2.337,   2.3361,    2.328,   2.3258,    2.318,   2.3144,   3.1102,   3.0949,   3.0726,   3.0311,   3.0232,   3.0136,   2.9879,   2.9879,   2.9847,     2.97,   2.9467,   2.9152,   2.9152,   2.9152,   2.9152,     2.87,     2.87,     2.87,     2.87,     2.87,   2.8629,   2.8544,   2.8514,   2.8451,   2.8372,   2.8339,    2.829,   2.8288,   2.8195,   2.7999,   3.1587,   3.1547,    3.153,   3.1309,   3.0789,   3.0706,   3.0661,   3.0595,   3.0568,   3.0454,   3.0395,   3.0395,   3.0237,    3.017,    3.017,    3.017,   2.9865,   2.9865,   2.9865,   2.9865,   2.9865,   2.9865,   2.9865,   2.9427,   2.9427,   2.9427,   2.9427,   2.9427,   2.9427,   2.9427,   3.5944,    3.575,   3.5412,   3.5412,   3.5394,   3.4939,   3.4928,   3.4928,   3.4928,    3.467,    3.467,    3.467,    3.467,    3.467,    3.449,   3.4446,   3.4399,   3.4323,   3.4323,   3.4323,   3.4323,   3.3827,   3.3827,   3.3827,   3.3827,   3.3827,   3.3827,   3.3827,   3.3827,   3.3827,    1.672,   1.6662,   1.6543,   1.7745,   1.9775,   2.1047,   2.1017,   1.9752,   2.3056,    2.797,    2.939,   1.6577,    1.966,   1.9682,   2.1054,   1.9404,    2.787,   2.9273,   2.9264,   2.9355,   1.7518,   1.7436,   1.7099,   1.6705,    1.913,   1.9182,   1.9173,    2.265,   2.9165,   1.7106,   1.8791,   1.8098,   1.9027,   2.0856,   1.9625,   1.6385,   1.6056,   1.6996,    1.758,   1.9566,   1.8963,   2.2009,   2.2536,   2.2345,   2.7133,   2.8956,    1.553,   1.7427,   1.7444,   1.8677,   2.2496,   2.1117,   1.4849,   1.4499,   2.0445,   1.7135,   2.2178,   2.7595,   1.5435,   1.8643,   1.9341,   2.2562,   2.0581,   2.8243,   1.2652,   1.6262,   1.5445,   1.6894,    1.966,    1.932,   2.0175,   2.6565,   1.5815,   1.7633,   2.2318,    2.122,    2.791,   3.1768,   3.0172,   1.4779,   1.6975,   1.5102,   1.6248,   2.7367,   2.7778,   2.7666,   1.2649,   1.3827,   1.7324,   1.9577,   1.4228,    1.252,   2.1961,   1.8934,   2.6864,   1.6708,   1.7167,   1.7854,   1.8366,   2.1449,   2.2155,   2.1571,   1.1702,   1.5272,    1.604,   1.7167,   1.5136,      2.7,   2.9021,   1.5784,   1.6906,   1.3352,   2.5521,   0.6623,   1.7077,   0.9439,   1.4728,    1.489,   1.8714,   1.9577,   2.6244,   1.0113,    1.331,   1.3268,    1.396,   1.9784,   1.1724,   2.0747,   2.5448,   2.5102,   0.9291,   1.1104,   1.1162,    1.294,    1.601,   1.6282,   2.1092,   1.1787,   1.1697,   1.6947,   1.3869,   1.8806,   1.4146,   1.7316,   1.5743,   2.9072,    3.118,   0.9842,    1.108,   2.7135,   1.0301,   1.2509,    1.692,   1.9015,   2.0828,   2.4946,   3.2751,   3.2751,   0.6454,   1.4136,    1.028,   1.2924,   1.5372,   1.5084,   2.3989,   3.2661,   0.9529,   0.7342,    1.098,   1.4491,   1.6291,   1.0858,   1.6537,    1.689,   1.8843,   1.9234,   2.6215,   0.3666,   0.6071,   2.0926,   2.6204,   3.0136,   1.5989,   1.4066,   1.5586,   2.0369,   2.0275,   0.9347,   0.8855,   1.0115,   1.8778,   1.6357,   1.0869,   2.4144,   2.4441,   1.0217,   0.1406,   1.7518,   0.2632,   1.1201,   1.2578,   0.3401,   2.9009,   1.6708,    1.015,   0.8001,   1.3645,   0.4571,     0.57,   2.1704,   2.5203,   0.0131,   1.3183,    1.694,   1.4656,   2.5426,   1.1559,   1.3487,   2.4844,   0.7168,   1.3376,   1.2641,   0.1581,   1.0988,   1.1811,   0.9323,   1.8863,   0.9287,   1.5555,   0.9445,   1.4228,   1.2945,   1.8429,   1.0352,   0.5952,   0.9915,   1.8067,   1.2876,   1.7677,   1.0298,   0.9652,   0.6914,   1.6334,  -0.2524,   1.6172,   1.1508,   2.1152,   1.8237,   1.2342,    2.002,   0.5596,   1.4951,   0.9799,   0.4652,   0.9766,  -0.0608,   3.1618,   0.5725,   0.2873,   0.5991,   0.6654,   1.2138,   0.7207,   0.6066,   2.5048,  -0.3362,   0.9214,   0.9504,    1.267,   2.6297,   1.0651,   1.2676,   0.8742,   2.3237,    0.838,   0.6566,   2.2234,   1.9017,   1.8437,   3.0132,   2.8935,  -0.4744,   0.9716,   0.2512,     -0.2,   2.2213,  -0.2262,   1.2028,   1.4076,  -0.1768,   1.0706,   0.6856,   1.3687,   0.0937,   0.3372,   -0.118,   -0.535,   0.5897,   0.4967,  -0.0661,   0.7568,   1.0018,   0.4147,   1.5218,   0.7357,   0.9676,   1.7164,  -0.4948,  -0.5102,   0.5274,  -0.1603,   2.3272,   0.1174,   0.3825,   0.4841,  -0.2851,  -0.0552,    1.114,   1.4182,    2.178,   2.3044,    2.589,   0.5242,   1.0923,   0.7781,   0.7731,   0.9599,  -0.2397,   0.3141,    1.571,   1.1238,   0.4613,  -0.8495,  -0.0172,  -0.2553,  -0.7524,   1.1658,  -0.2931,    0.472,   0.7912,   0.1937,  -0.7525,  -0.4966,   1.0468,    0.022,  -0.8202,   1.5673,   2.5114,   2.4945,   0.9126,   0.2623,   0.5549,   0.4108,   1.1974,   -0.098,   1.8442,  -0.0077,  -0.2345,   0.5377,  -0.5813,   0.3406,  -0.1164,   -0.521,   0.3868,  -0.2872,   1.9384,   1.4549,  -0.7591,  -1.9081,   1.0886,  -1.0116,   0.5829,   1.3492,   0.4218,   0.2691,   0.2997,   0.0224,     1.03,  -1.0979,   0.8933,  -2.3563,  -1.2153,   0.2013,   0.7682,   0.7145,   0.4938,  -0.0184,   0.2755,   0.5756,   0.2405,   0.8296,  -1.2828,   0.1836 ],
"Freq": [    12341,     5256,     3593,     3340,     9238,     2922,     3195,     3018,     2425,     3185,     4867,     2170,     1605,    20857,     1508,     3782,     2129,     1557,      901,      696,     2889,     1853,     6358,     2152,      706,     1001,     3315,     1564,     1445,      489, 419.7476, 45.19106, 37.04853, 301.6809, 32.97726,   28.906,   28.906,  53.3336, 146.9727, 24.83473,  53.3336, 20.76346, 20.76346, 20.76346, 20.76346, 73.68993, 37.04853, 16.69219, 16.69219, 16.69219, 16.69219, 16.69219,   28.906,  623.311, 2492.023, 45.19106, 12.62093, 12.62093, 12.62093, 12.62093,  122.307,  72.4987, 50.36169, 44.82744, 39.29319, 3260.228, 116.7727, 33.75893, 33.75893, 66.96444, 28.22468, 28.22468, 28.22468, 149.9782, 22.69043, 22.69043, 22.69043, 22.69043, 22.69043, 22.69043, 22.69043, 847.2939, 17.15618, 17.15618, 17.15618, 17.15618, 17.15618, 17.15618, 17.15618, 17.15618, 137.5917, 73.93715, 73.93715, 64.14415, 88.62665, 44.55815, 44.55815, 93.52315, 39.66165, 39.66165, 132.6952, 34.76515, 34.76515, 29.86865, 29.86865, 29.86865, 49.45465, 24.97215, 24.97215, 24.97215, 24.97215, 24.97215, 754.5507, 108.2127, 34.76515, 20.07565, 20.07565, 20.07565, 20.07565, 20.07565, 108.7989,  81.6745, 30.43957, 27.42575, 27.42575, 96.74359,  66.6054,  223.324, 99.75741, 21.39812, 21.39812, 21.39812, 21.39812, 21.39812, 45.50867, 129.8956,  18.3843,  18.3843,  18.3843,  18.3843,  18.3843,  18.3843, 72.63304, 36.46721, 15.37048, 15.37048, 15.37048, 15.37048, 15.37048, 15.37048, 395.3864, 254.3449, 188.5255, 146.2131, 99.19922, 85.09506, 61.58814, 179.1228, 94.49783, 47.48398, 47.48398, 94.49783, 99.19922,  42.7826,  42.7826,  42.7826,  42.7826,  42.7826,  42.7826, 38.08122, 113.3034, 33.37983, 33.37983, 113.3034, 28.67845, 28.67845, 28.67845, 28.67845, 28.67845, 28.67845, 181.2544, 385.4551,  61.2602, 25.47245, 473.8718, 21.26213, 21.26213, 46.52407, 38.10342, 14.94665, 244.4092, 23.36729, 12.84148, 12.84148, 10.73632, 10.73632, 10.73632, 48.62923, 17.05181, 57.04988, 273.8815, 8.631162, 8.631162, 8.631162, 8.631162, 8.631162, 8.631162, 8.631162, 27.57762, 1962.221, 354.2884, 270.4883, 126.1658, 74.95458, 65.64345, 121.5102, 56.33232, 56.33232, 56.33232, 51.67676,  177.377, 42.36563, 42.36563, 42.36563, 37.71007, 74.95458,  33.0545,  33.0545,  33.0545, 28.39894, 28.39894, 28.39894, 47.02119, 47.02119, 56.33232, 130.8213, 23.74338, 23.74338, 23.74338, 23.74338, 152.1905, 60.31698, 128.2235, 56.32248, 52.32798, 427.8112, 36.34997, 36.34997, 36.34997, 811.2834,  96.2675, 32.35547, 56.32248, 28.36096, 28.36096, 28.36096, 28.36096, 28.36096, 28.36096,  132.218, 24.36646, 24.36646, 24.36646, 24.36646, 220.0971, 36.34997,  108.251, 48.33347, 288.0036, 20.37196, 261.2899, 261.2899, 73.00262, 142.3716, 36.66648, 33.36319, 26.75662, 26.75662, 99.42891, 23.45333, 20.15005, 16.84676, 16.84676, 16.84676, 16.84676, 13.54347, 13.54347, 13.54347, 13.54347, 13.54347, 20.15005, 92.82234,  30.0599, 33.36319, 39.96976, 23.45333, 66.39605, 20.15005, 33.36319, 10.24019, 284.4028, 205.6872, 106.4371, 65.36815,  75.6354, 31.14399, 72.21298, 61.94573, 27.72157, 51.67849, 24.29916, 24.29916, 157.7734, 20.87674, 20.87674, 20.87674, 17.45432, 17.45432, 17.45432, 17.45432, 17.45432, 17.45432, 17.45432, 14.03191, 14.03191, 14.03191, 14.03191, 14.03191, 14.03191, 14.03191, 53.51765, 41.69055, 29.86344, 29.86344, 118.5667, 38.73377, 20.99311, 20.99311, 20.99311, 18.03634, 18.03634, 18.03634, 18.03634, 18.03634, 35.77699, 35.77699, 23.94989, 15.07956, 15.07956, 15.07956, 15.07956, 12.12278, 12.12278, 12.12278, 12.12278, 12.12278, 12.12278, 12.12278, 12.12278, 12.12278, 1661.484,  41.1198, 94.04627,  72.4987, 33.45339, 150.9144, 127.4075, 425.4531, 323.9541, 271.1998, 48.25607,   28.906, 48.52249, 36.46721,  42.7826, 126.5202, 248.0768, 48.25607, 44.83365, 20.87674, 50.36169, 61.43019, 172.1152, 542.9101, 154.0062, 246.5144,  202.306, 70.29901, 37.98882,  122.307, 39.66165, 191.4532, 132.9094, 61.58814, 21.26213, 45.19106, 797.4856, 78.03295, 392.2097, 564.6363, 52.83955, 182.0325, 51.67676, 70.29901, 330.6589, 37.98882, 216.1843, 333.4517, 255.1077,  61.2602, 120.2345, 1034.975, 2053.761, 2889.433, 70.99091, 591.7609,  84.2657, 219.3769, 163.2578, 63.59158,  291.956, 68.30598, 651.5033,  75.6354, 2679.301, 194.2522, 1430.268, 425.2499, 188.5255, 263.7477, 1003.019, 414.4546,  65.5474, 1157.011, 60.98789, 256.0476,  30.0599, 94.91252, 363.9792, 404.5538, 253.4622, 1269.623, 471.7667, 43.27305,  30.0599, 109.8596, 4118.446, 2302.859, 169.0753, 165.0186,  1227.52, 513.3868, 65.64345, 859.2174, 140.6613, 127.7987, 132.9094,  81.6745, 57.04988, 112.2455, 72.30049,  100.262, 725.0926, 299.1762, 181.6602, 503.5183, 379.1396,  96.1699, 227.9675, 89.10145, 44.82744, 751.7532, 89.51905, 5818.248, 39.29319, 3991.137, 404.1531,   322.78, 340.3217, 236.0751,  113.282,  761.734, 167.3291, 568.4837, 402.0027, 94.49783, 1134.893, 112.1991, 86.21577, 171.4631, 1026.366, 581.6498, 1283.373, 627.1758, 154.0062,  123.868,  84.2657, 301.6809,  387.951, 88.62665, 340.8629, 127.4075, 282.3022, 391.5329, 863.2119, 24.29916, 35.77699,  623.311, 459.8963, 36.66648,   395.32, 1128.802, 235.5394, 186.6881, 112.2455, 106.4371, 18.03634, 18.03634,   1688.5,  122.307, 1018.972, 945.4484, 155.9925, 799.2998, 102.7322, 18.03634,  501.173, 993.7963, 281.3245, 196.3497, 103.3162, 627.1758, 249.6435, 216.7338,  177.377, 154.0992, 43.27305, 2561.234, 2489.716, 88.92127, 43.27305, 38.73377, 117.8403,  202.306, 414.8107,  100.262, 241.4702, 476.4991, 542.9101, 382.4168, 113.3034, 101.2583, 442.2944,  113.282, 99.59231, 285.3958, 3343.241, 200.6548, 2236.391, 343.8768,  536.428, 2722.184, 41.69055, 83.73015, 940.7471, 1797.513, 470.6775, 859.4445, 1044.371, 122.5519,  97.8693, 2659.289, 400.0878, 200.6548, 303.9816, 58.52332,  210.855, 177.0441, 91.95574, 366.8212, 172.0891, 447.3997,  1071.15, 250.2112, 229.3516, 785.6014, 130.8213, 795.3053, 300.9294, 288.3345,  149.677, 187.5699, 168.7979, 195.8279, 575.9408, 311.7744, 172.1012, 142.4882, 154.0992, 187.6854, 238.5262, 357.9342, 186.6881, 1781.469, 207.3311, 219.1473, 103.0147, 157.7734, 298.4216,  96.2675, 469.6615, 200.6548, 205.3207, 431.3817, 277.5727, 1630.156, 20.99311, 349.2113, 534.2082, 434.2913, 563.7888, 279.7994,  273.182, 512.3397,  55.1009, 919.2392, 418.8934, 363.5995, 220.0971, 38.73377, 217.2964, 268.4491, 304.2327, 53.51765, 235.5217, 340.8629, 63.09277, 86.21577, 109.8596, 23.94989, 26.90666, 826.8743, 338.9698, 519.6847, 750.1763, 53.51765,  1053.58, 200.1245, 139.0683, 586.6696, 161.0467, 278.0918, 186.6881,  456.389, 316.0058, 621.1481, 1307.455, 249.5947, 328.6157,  432.225, 215.9357,  291.956, 372.9107, 109.3388, 195.2242, 229.3516, 126.1658, 523.9719, 480.3467, 301.6833, 448.8278, 38.73377, 395.1117, 205.1341,   195.42, 357.9342, 371.3483, 182.0325, 136.2125, 38.73377, 35.77699, 29.86344, 196.3497, 106.0355, 144.0837, 80.12864, 123.5492, 289.3832, 315.4629, 76.30591, 62.38798, 129.1585, 434.2913, 260.0421, 274.6937, 404.4015, 106.4371,   195.42, 140.6613, 216.1843, 220.8322, 465.9072,  414.192, 152.1905,  267.566, 178.7078, 41.69055, 29.86344, 29.86344, 187.1582, 200.1245,  180.152, 236.5406, 149.4436, 220.0971,  75.6354, 266.1975, 262.5036, 205.2411, 237.8993, 232.4693, 268.4491, 215.9357, 182.0325,  188.141, 32.82022, 35.77699, 250.4484, 270.4883, 82.91248, 266.1975, 193.1858, 35.77699,  230.838, 41.69055, 168.0659, 236.5406, 147.3847, 176.1575, 154.0992, 50.56088, 181.6602,  190.172, 207.3311,  75.6354, 152.2812, 35.77699,  79.6092, 32.82022,  79.6092, 194.2522, 154.0992,  79.6092 ],
"Total": [    12341,     5256,     3593,     3340,     9238,     2922,     3195,     3018,     2425,     3185,     4867,     2170,     1605,    20857,     1508,     3782,     2129,     1557,      901,      696,     2889,     1853,     6358,     2152,      706,     1001,     3315,     1564,     1445,      489, 445.9933, 49.04943,  40.9069, 336.2534, 36.83563, 32.76436, 32.76436, 60.49525, 166.8845, 28.69309, 62.71954, 24.62183, 24.62183, 24.62183, 24.62183, 87.81555, 45.56246, 20.55056, 20.55056, 20.55056, 20.55056, 20.55056, 36.06765, 781.9932, 3195.874, 58.76693, 16.47929, 16.47929, 16.47929, 16.47929,  126.019, 76.21076, 54.07376, 48.53951, 43.00525, 3593.235, 129.2116,   37.471,   37.471, 75.57301, 31.93675, 31.93675, 31.93675, 171.9317,  26.4025,  26.4025,  26.4025,  26.4025,  26.4025,  26.4025,  26.4025, 1005.194, 20.86825, 20.86825, 20.86825, 20.86825, 20.86825, 20.86825, 20.86825, 20.86825, 141.3675,   77.713,   77.713,    67.92, 95.82491, 48.33399, 48.33399, 102.0004, 43.43749, 43.43749, 146.3809, 38.54099, 38.54099, 33.64449, 33.64449, 33.64449, 56.53378, 28.74799, 28.74799, 28.74799, 28.74799, 28.74799, 871.7088,  126.293, 40.64616, 23.85149, 23.85149, 23.85149, 23.85149, 23.85149,  112.763, 85.63861, 34.40368, 31.38987, 31.38987, 111.2335, 77.17609, 263.3802, 117.8257, 25.36223, 25.36223, 25.36223, 25.36223, 25.36223, 54.36928,  157.142, 22.34841, 22.34841, 22.34841, 22.34841, 22.34841, 22.34841, 88.81095, 44.64165, 19.33459, 19.33459, 19.33459, 19.33459, 19.33459, 19.33459, 399.1818, 258.1403, 192.3209, 150.0084, 102.9946, 88.89042, 65.38349, 192.4469, 101.5965, 51.27934, 51.27934, 102.2877, 107.6501, 46.57795, 46.57795, 46.57795, 46.57795, 46.57795, 46.57795, 41.87657, 125.0877, 37.17519, 37.17519, 127.6245,  32.4738,  32.4738,  32.4738,  32.4738,  32.4738,  32.4738, 185.3094, 396.3549, 65.31518, 29.52743, 550.3097, 25.31711, 25.31711, 56.60668, 46.85978, 19.00162, 313.4901, 30.43609, 16.89646, 16.89646,  14.7913,  14.7913,  14.7913, 67.52959,  24.1206, 81.07045, 396.4831, 12.68614, 12.68614, 12.68614, 12.68614, 12.68614, 12.68614, 12.68614, 41.03536, 2922.668, 358.0883, 274.2882, 129.9657, 78.75451, 69.44339, 128.7326, 60.13226, 60.13226, 60.13226, 55.47669, 192.2454, 46.16557, 46.16557, 46.16557,    41.51, 82.82578, 36.85444, 36.85444, 36.85444, 32.19888, 32.19888, 32.19888, 53.77791, 54.12442,  65.1942, 151.5013, 27.54331, 27.54331, 27.54331, 27.54331, 156.0566, 64.18302, 136.9861, 60.18852, 56.19402, 468.0134, 40.21601, 40.21601, 40.21601,  901.461, 106.9784, 36.22151, 63.61094, 32.22701, 32.22701, 32.22701, 32.22701, 32.22701, 32.22701, 152.6005,  28.2325,  28.2325,  28.2325,  28.2325, 256.0316, 42.32117, 127.0541, 56.85508, 341.4527,   24.238, 265.2251, 269.2964, 76.93779,  156.401, 40.60164, 37.29835, 30.69178, 30.69178, 114.4192,  27.3885, 24.08521, 20.78192, 20.78192, 20.78192, 20.78192, 17.47864, 17.47864, 17.47864, 17.47864, 17.47864, 26.19037, 121.6861, 39.52265, 44.14319,  53.3077,   31.383, 89.27767, 27.09903, 45.28736, 14.17535, 293.2225, 212.9138, 110.3604,  69.2914, 84.45515, 35.06724, 81.67049, 70.52455, 31.64482,   59.673, 28.22241, 28.22241, 186.1791, 24.79999, 24.79999, 24.79999, 21.37757, 21.37757, 21.37757, 21.37757, 21.37757, 21.37757, 21.37757, 17.95516, 17.95516, 17.95516, 17.95516, 17.95516, 17.95516, 17.95516, 57.48747, 45.66036, 33.83326, 33.83326, 134.5667, 46.00687, 24.96293, 24.96293, 24.96293, 22.00615, 22.00615, 22.00615, 22.00615, 22.00615, 44.44819, 44.64331, 30.02487, 19.04937, 19.04937, 19.04937, 19.04937,  16.0926,  16.0926,  16.0926,  16.0926,  16.0926,  16.0926,  16.0926,  16.0926,  16.0926, 2170.141, 54.01962,  125.029, 88.26604, 42.11889, 171.8422,  145.509, 635.4031, 388.8698, 376.5199, 61.97232, 38.29861, 61.79773, 46.34488, 48.68312, 195.6524,   347.88, 62.70513, 58.30897, 26.90515, 62.72382, 77.14049, 223.5327,  733.477, 206.8255, 389.7847, 320.1592, 83.50172, 49.90108, 158.7349, 48.13888, 249.0494, 180.3456, 71.48316, 32.16194, 61.03294, 1149.649, 102.3964, 537.2986, 745.5982,  85.3934, 230.5387, 62.08327, 86.08246, 499.1426, 50.95353, 318.0353, 463.8441, 354.2595, 101.8798,  152.632, 1508.139, 3340.356, 4867.108, 85.85476, 1148.166,  104.925, 337.1397, 242.4616, 89.66492, 394.2987, 86.13872, 1001.614, 108.9417, 5256.017, 274.3086, 2425.752, 714.2027, 246.6234, 356.9628, 1605.924, 706.0372,  93.7202, 1853.519, 74.88673, 369.3011, 41.98407, 154.8054,   696.37, 662.6429, 422.2416, 3018.876, 1000.237, 63.81097, 42.54314, 167.6443, 9238.292, 5256.017, 272.0199, 217.6692, 3185.086, 1020.507, 83.53205, 1557.405, 232.5634, 191.0345, 217.2117, 124.6172, 97.86996, 158.2148, 94.97207, 139.6094, 1564.207, 516.2633, 290.2969, 845.1713, 898.4438, 156.8529, 489.3704, 131.9855,  59.3564, 2129.302, 158.7748, 20857.24, 51.14779, 12341.27, 842.9509, 662.4147,  599.175, 401.2949,  199.275, 1926.209, 307.3633, 1198.622, 790.9594, 122.0938, 3782.925, 161.2063,   154.04, 338.1229, 2817.761, 1375.793, 3340.356, 1564.207, 282.5473, 221.1647,   116.97, 645.2836, 864.8101, 129.3484, 774.6984, 181.5202, 738.5604, 792.7911, 2152.807, 32.21691, 61.88382, 1619.458, 1090.446, 55.33777, 981.0883, 3018.876, 405.2365, 318.9426, 168.3642, 213.1869, 26.66171, 26.66171,  6358.02, 213.6391, 3315.589, 2425.752, 361.0044, 2129.302, 212.3707, 26.90265, 1343.516, 3315.589, 652.3413, 366.3302, 161.0037, 1926.209, 446.2666, 373.9957, 308.3033, 257.5641, 71.60687, 12341.27, 12341.27, 125.4866, 71.68224, 74.36935,  216.665, 533.5259, 998.5955, 157.4433, 723.6732, 1343.516, 1607.972, 998.5955, 161.8885, 212.3707, 1605.924, 245.8329, 209.8029, 714.2027, 20857.24, 398.1702, 12341.27, 1020.507, 1424.716, 20857.24, 89.59988, 125.1526, 3185.086, 9238.292, 1375.793, 3782.925,  6358.02, 318.3678, 307.7711, 20857.24, 1000.237, 421.8625, 845.1713,  111.719, 476.5413, 494.7435, 299.7336, 1245.304,  410.883, 1445.905,  6358.02, 662.6429, 640.3827, 2889.127,  226.932, 3782.925, 1445.905, 805.0848, 388.3986, 553.3428, 608.4512, 483.5098, 2889.127, 1245.304, 643.2207, 312.4323, 300.9618, 465.8917, 652.3413, 1424.716, 417.0032, 20857.24, 384.4156, 746.3813, 301.5211, 618.1366, 993.6859, 156.5502, 2889.127, 514.7194, 553.3428, 2152.807, 950.8959, 20857.24, 34.75593, 1414.457, 3185.086, 2170.141, 3315.589, 950.8959, 923.7577,  6358.02, 109.2441, 9238.292, 1557.405, 1607.972, 746.3813, 109.1773, 681.3078, 706.0372, 2889.127, 204.8577, 809.6063, 1607.972, 155.4423, 293.0248, 421.8625, 46.00262, 58.25581, 9238.292, 1198.622, 4867.108, 20857.24,  226.932, 12341.27, 723.6732, 774.6984, 4867.108, 396.4102, 1508.139, 543.3785, 2889.127, 1619.458,  6358.02, 20857.24, 993.6859, 2152.807, 3315.589, 805.0848, 1001.614, 2817.761, 543.3785, 2129.302, 792.7911, 259.3797, 20857.24,  6358.02, 1619.458, 3782.925, 147.7524, 3195.874, 3185.086, 2922.668, 3782.925, 2817.761, 683.5341, 397.1127, 171.5167, 139.6094, 87.67338, 923.7577, 809.6063, 1605.924, 1445.905, 1148.166, 2922.668, 2152.807, 361.0044, 792.7911, 1853.519, 9238.292, 3185.086, 2817.761, 9238.292, 805.0848,  6358.02, 2129.302, 681.3078, 1445.905, 9238.292,  6358.02, 643.2207, 2817.761, 9238.292,  340.013,  94.7498, 96.36571, 683.5341, 1853.519, 1245.304, 1090.446, 516.2633, 2922.668, 290.2969, 1926.209, 3018.876, 1090.446, 4867.108, 1149.649, 2817.761, 2889.127, 1414.457, 3018.876, 184.6771, 326.4788, 4867.108, 20857.24, 635.4031, 5256.017, 981.0883,  362.866, 1414.457, 1245.304, 1424.716, 1607.972, 418.1509,  6358.02,  721.548, 20857.24, 4867.108, 1414.457, 898.4438, 898.4438, 738.5604, 1424.716, 1375.793,  721.548, 1424.716, 608.4512,  6358.02, 1508.139 ],
"Category": [ "Default", "Default", "Default", "Default", "Default", "Default", "Default", "Default", "Default", "Default", "Default", "Default", "Default", "Default", "Default", "Default", "Default", "Default", "Default", "Default", "Default", "Default", "Default", "Default", "Default", "Default", "Default", "Default", "Default", "Default", "Topic1", "Topic1", "Topic1", "Topic1", "Topic1", "Topic1", "Topic1", "Topic1", "Topic1", "Topic1", "Topic1", "Topic1", "Topic1", "Topic1", "Topic1", "Topic1", "Topic1", "Topic1", "Topic1", "Topic1", "Topic1", "Topic1", "Topic1", "Topic1", "Topic1", "Topic1", "Topic1", "Topic1", "Topic1", "Topic1", "Topic2", "Topic2", "Topic2", "Topic2", "Topic2", "Topic2", "Topic2", "Topic2", "Topic2", "Topic2", "Topic2", "Topic2", "Topic2", "Topic2", "Topic2", "Topic2", "Topic2", "Topic2", "Topic2", "Topic2", "Topic2", "Topic2", "Topic2", "Topic2", "Topic2", "Topic2", "Topic2", "Topic2", "Topic2", "Topic2", "Topic3", "Topic3", "Topic3", "Topic3", "Topic3", "Topic3", "Topic3", "Topic3", "Topic3", "Topic3", "Topic3", "Topic3", "Topic3", "Topic3", "Topic3", "Topic3", "Topic3", "Topic3", "Topic3", "Topic3", "Topic3", "Topic3", "Topic3", "Topic3", "Topic3", "Topic3", "Topic3", "Topic3", "Topic3", "Topic3", "Topic4", "Topic4", "Topic4", "Topic4", "Topic4", "Topic4", "Topic4", "Topic4", "Topic4", "Topic4", "Topic4", "Topic4", "Topic4", "Topic4", "Topic4", "Topic4", "Topic4", "Topic4", "Topic4", "Topic4", "Topic4", "Topic4", "Topic4", "Topic4", "Topic4", "Topic4", "Topic4", "Topic4", "Topic4", "Topic4", "Topic5", "Topic5", "Topic5", "Topic5", "Topic5", "Topic5", "Topic5", "Topic5", "Topic5", "Topic5", "Topic5", "Topic5", "Topic5", "Topic5", "Topic5", "Topic5", "Topic5", "Topic5", "Topic5", "Topic5", "Topic5", "Topic5", "Topic5", "Topic5", "Topic5", "Topic5", "Topic5", "Topic5", "Topic5", "Topic5", "Topic6", "Topic6", "Topic6", "Topic6", "Topic6", "Topic6", "Topic6", "Topic6", "Topic6", "Topic6", "Topic6", "Topic6", "Topic6", "Topic6", "Topic6", "Topic6", "Topic6", "Topic6", "Topic6", "Topic6", "Topic6", "Topic6", "Topic6", "Topic6", "Topic6", "Topic6", "Topic6", "Topic6", "Topic6", "Topic6", "Topic7", "Topic7", "Topic7", "Topic7", "Topic7", "Topic7", "Topic7", "Topic7", "Topic7", "Topic7", "Topic7", "Topic7", "Topic7", "Topic7", "Topic7", "Topic7", "Topic7", "Topic7", "Topic7", "Topic7", "Topic7", "Topic7", "Topic7", "Topic7", "Topic7", "Topic7", "Topic7", "Topic7", "Topic7", "Topic7", "Topic8", "Topic8", "Topic8", "Topic8", "Topic8", "Topic8", "Topic8", "Topic8", "Topic8", "Topic8", "Topic8", "Topic8", "Topic8", "Topic8", "Topic8", "Topic8", "Topic8", "Topic8", "Topic8", "Topic8", "Topic8", "Topic8", "Topic8", "Topic8", "Topic8", "Topic8", "Topic8", "Topic8", "Topic8", "Topic8", "Topic9", "Topic9", "Topic9", "Topic9", "Topic9", "Topic9", "Topic9", "Topic9", "Topic9", "Topic9", "Topic9", "Topic9", "Topic9", "Topic9", "Topic9", "Topic9", "Topic9", "Topic9", "Topic9", "Topic9", "Topic9", "Topic9", "Topic9", "Topic9", "Topic9", "Topic9", "Topic9", "Topic9", "Topic9", "Topic9", "Topic10", "Topic10", "Topic10", "Topic10", "Topic10", "Topic10", "Topic10", "Topic10", "Topic10", "Topic10", "Topic10", "Topic10", "Topic10", "Topic10", "Topic10", "Topic10", "Topic10", "Topic10", "Topic10", "Topic10", "Topic10", "Topic10", "Topic10", "Topic10", "Topic10", "Topic10", "Topic10", "Topic10", "Topic10", "Topic10", "Topic11", "Topic11", "Topic11", "Topic11", "Topic11", "Topic11", "Topic11", "Topic11", "Topic11", "Topic11", "Topic11", "Topic11", "Topic11", "Topic11", "Topic11", "Topic11", "Topic11", "Topic11", "Topic11", "Topic11", "Topic11", "Topic11", "Topic11", "Topic11", "Topic11", "Topic11", "Topic11", "Topic11", "Topic11", "Topic11", "Topic1", "Topic1", "Topic1", "Topic2", "Topic4", "Topic5", "Topic5", "Topic6", "Topic8", "Topic9", "Topic10", "Topic1", "Topic4", "Topic4", "Topic5", "Topic6", "Topic9", "Topic10", "Topic10", "Topic10", "Topic2", "Topic2", "Topic2", "Topic2", "Topic4", "Topic6", "Topic6", "Topic7", "Topic10", "Topic2", "Topic3", "Topic3", "Topic4", "Topic5", "Topic6", "Topic1", "Topic2", "Topic2", "Topic3", "Topic5", "Topic6", "Topic7", "Topic7", "Topic7", "Topic9", "Topic10", "Topic1", "Topic3", "Topic3", "Topic6", "Topic8", "Topic8", "Topic2", "Topic2", "Topic5", "Topic6", "Topic7", "Topic10", "Topic1", "Topic4", "Topic5", "Topic8", "Topic8", "Topic10", "Topic1", "Topic2", "Topic3", "Topic4", "Topic5", "Topic5", "Topic8", "Topic10", "Topic1", "Topic5", "Topic7", "Topic8", "Topic9", "Topic11", "Topic11", "Topic2", "Topic4", "Topic6", "Topic6", "Topic9", "Topic9", "Topic10", "Topic3", "Topic4", "Topic4", "Topic5", "Topic6", "Topic1", "Topic7", "Topic8", "Topic10", "Topic3", "Topic4", "Topic4", "Topic6", "Topic8", "Topic8", "Topic8", "Topic1", "Topic3", "Topic3", "Topic5", "Topic6", "Topic10", "Topic11", "Topic2", "Topic2", "Topic6", "Topic9", "Topic1", "Topic2", "Topic3", "Topic4", "Topic4", "Topic7", "Topic8", "Topic10", "Topic1", "Topic1", "Topic3", "Topic3", "Topic5", "Topic6", "Topic7", "Topic9", "Topic10", "Topic1", "Topic2", "Topic3", "Topic4", "Topic4", "Topic4", "Topic7", "Topic1", "Topic2", "Topic3", "Topic4", "Topic5", "Topic6", "Topic7", "Topic8", "Topic10", "Topic11", "Topic1", "Topic2", "Topic9", "Topic1", "Topic5", "Topic5", "Topic7", "Topic8", "Topic10", "Topic11", "Topic11", "Topic2", "Topic2", "Topic4", "Topic5", "Topic6", "Topic8", "Topic9", "Topic11", "Topic1", "Topic1", "Topic1", "Topic3", "Topic3", "Topic4", "Topic5", "Topic5", "Topic7", "Topic7", "Topic9", "Topic1", "Topic4", "Topic7", "Topic9", "Topic11", "Topic4", "Topic6", "Topic7", "Topic8", "Topic9", "Topic2", "Topic2", "Topic2", "Topic5", "Topic6", "Topic6", "Topic10", "Topic10", "Topic1", "Topic2", "Topic7", "Topic2", "Topic4", "Topic5", "Topic6", "Topic11", "Topic3", "Topic5", "Topic7", "Topic7", "Topic1", "Topic6", "Topic9", "Topic11", "Topic3", "Topic5", "Topic7", "Topic8", "Topic10", "Topic2", "Topic6", "Topic11", "Topic1", "Topic4", "Topic7", "Topic1", "Topic3", "Topic4", "Topic5", "Topic7", "Topic8", "Topic9", "Topic2", "Topic6", "Topic6", "Topic9", "Topic1", "Topic4", "Topic6", "Topic9", "Topic3", "Topic7", "Topic1", "Topic2", "Topic3", "Topic7", "Topic4", "Topic5", "Topic6", "Topic10", "Topic10", "Topic7", "Topic8", "Topic6", "Topic7", "Topic2", "Topic3", "Topic4", "Topic8", "Topic11", "Topic2", "Topic3", "Topic4", "Topic7", "Topic7", "Topic1", "Topic9", "Topic10", "Topic2", "Topic5", "Topic7", "Topic8", "Topic11", "Topic4", "Topic5", "Topic9", "Topic11", "Topic3", "Topic4", "Topic9", "Topic9", "Topic10", "Topic11", "Topic11", "Topic1", "Topic5", "Topic8", "Topic9", "Topic11", "Topic5", "Topic8", "Topic9", "Topic1", "Topic2", "Topic6", "Topic7", "Topic1", "Topic2", "Topic4", "Topic5", "Topic2", "Topic6", "Topic2", "Topic3", "Topic5", "Topic7", "Topic9", "Topic9", "Topic4", "Topic7", "Topic10", "Topic3", "Topic4", "Topic2", "Topic11", "Topic4", "Topic9", "Topic10", "Topic3", "Topic2", "Topic7", "Topic8", "Topic11", "Topic11", "Topic11", "Topic3", "Topic9", "Topic10", "Topic11", "Topic10", "Topic3", "Topic5", "Topic9", "Topic11", "Topic9", "Topic4", "Topic8", "Topic3", "Topic6", "Topic10", "Topic10", "Topic10", "Topic1", "Topic3", "Topic5", "Topic5", "Topic8", "Topic6", "Topic9", "Topic11", "Topic11", "Topic11", "Topic4", "Topic8", "Topic8", "Topic1", "Topic7", "Topic8", "Topic10", "Topic2", "Topic4", "Topic4", "Topic7", "Topic1", "Topic5", "Topic3", "Topic7", "Topic8", "Topic11", "Topic11", "Topic4", "Topic7", "Topic9", "Topic2", "Topic4", "Topic11", "Topic5", "Topic11", "Topic7", "Topic1", "Topic3", "Topic8", "Topic7", "Topic11", "Topic3", "Topic4", "Topic5", "Topic10", "Topic3", "Topic11", "Topic9", "Topic11", "Topic9", "Topic2", "Topic7", "Topic9" ] 
},
"token.table": {
 "Term": [ "가능", "가능", "가능", "가능", "가능", "가능", "가능", "가입", "가입", "가입", "가입", "가정", "가정", "가정", "가정", "가정", "가정", "가족", "가족", "가족", "가족", "가족", "가족", "각서", "갈취", "갈취", "감당", "감당", "감당", "감독원", "감독원", "강남", "강남", "강요", "강요", "강요", "강하다", "강하다", "갚다", "갚다", "개정", "개정", "거금", "거래", "거래", "거래", "거래", "거래", "걱정", "걱정", "걱정", "걱정", "걱정", "걱정", "걱정", "걱정", "걱정", "걸다", "걸다", "걸다", "걸다", "걸다", "걸다", "걸다", "걸리다", "걸리다", "걸리다", "걸리다", "걸리다", "걸리다", "걸리다", "걸리다", "검정고시", "검정고시", "검찰청", "검찰청", "겁나다", "겁나다", "겁나다", "게임", "게임", "게임", "게임", "게임", "게임", "견디다", "결과", "결과", "결과", "결과", "결과", "결심", "결심", "경기", "경기", "경기", "경력", "경력", "경위", "경위", "경찰", "경찰", "경찰", "경찰", "경찰", "경찰", "경찰", "경찰", "경찰관", "경찰관", "경찰관", "경찰서", "경찰서", "경찰서", "경찰서", "경찰서", "경찰서", "계정", "계정", "계정", "계정", "계정", "계좌", "계좌", "계좌", "계좌", "계좌", "계좌", "계좌", "계좌", "계좌", "계좌번호", "계좌번호", "계좌번호", "고등학교", "고등학교", "고등학교", "고등학교", "고등학교", "고등학교", "고등학교", "고등학생", "고등학생", "고등학생", "고등학생", "고등학생", "고등학생", "고등학생", "고등학생", "고등학생", "고등학생", "고르다", "고르다", "고소", "고소", "고소", "고소", "공갈", "공갈", "공갈", "공갈", "공무원", "공무원", "공무원", "공무원", "공부", "공부", "공부", "공부", "공부", "공부", "공소시효", "공소시효", "공짜", "공짜", "공판", "공판", "과거", "과거", "관계", "관계", "관계", "관계", "관할", "관할", "광고", "광고", "광고", "광고", "교도소", "교도소", "교사", "교사", "교육", "교육", "교육", "구글", "구글", "구입", "구입", "구하다", "구하다", "국민은행", "국민은행", "군인", "군인", "군인", "군인", "궁금증", "궁금증", "권유", "권유", "권유", "권유", "권유", "권유", "그래프", "그래프", "그래프", "그래프", "그램", "그램", "그림장", "그림장", "금", "금", "금", "금", "금", "금액", "금액", "금액", "금액", "금액", "금액", "금액", "금액", "금융", "금융", "급하다", "급하다", "급하다", "기간", "기간", "기간", "기간", "기간", "기록", "기록", "기록", "기록", "기부", "기부", "기부", "기소", "기소", "기소유예", "기소유예", "기소유예", "기소유예", "기한", "기한", "기한", "깨다", "꺼내다", "꽁", "꽁", "꽁머니", "꽁머니", "꽁머니", "꾸다", "꾸다", "꾸다", "꿈", "꿈", "꿈", "꿈", "꿈", "꿈", "끊다", "끊다", "끊다", "끊다", "끊다", "끊다", "끊다", "나오다", "나오다", "나오다", "나오다", "나오다", "나오다", "나오다", "나오다", "나오다", "나이", "나이", "나이", "나이", "나이", "나이", "날다", "날다", "날짜", "날짜", "날짜", "날짜", "남", "남", "남", "남", "남", "남", "남다", "남다", "남다", "남다", "남다", "남다", "남다", "남자", "남자", "남자", "남자", "남자", "남친", "남친", "내역", "내역", "내역", "내역", "내역", "내역", "내역", "내용", "내용", "내용", "내용", "내용", "넣다", "넣다", "넣다", "넣다", "넣다", "넣다", "네임드", "네임드", "노다", "노다", "노다", "녹음", "녹음", "놀다", "놀다", "누나", "누나", "누나", "누나", "누르다", "누르다", "눈물", "눈물", "뉴스", "뉴스", "닝", "닝", "다니다", "다니다", "다니다", "다니다", "다니다", "다니다", "다니다", "다니다", "다니다", "다니다", "다리", "다리", "다행", "다행", "다행", "다행", "단도박", "단도박", "단도박", "단도박", "단속", "단속", "달다", "달다", "달다", "달다", "달다", "달다", "달다", "담", "담", "담배", "담배", "담보", "담보", "담보", "당첨", "당첨", "대구", "대구", "대구", "대리", "대리", "대상자", "대상자", "대순가", "대순가", "대여금", "대여금", "대출", "대출", "대출", "대출", "대포", "대포", "더치트", "더치트", "덜다", "도박", "도박", "도박", "도박", "도박", "도박", "도박", "도박", "도박", "도박", "도박", "도박장", "도박장", "도박장", "도벽", "도벽", "도요", "도요", "도움", "도움", "도움", "도움", "도움", "도움", "독촉", "돈", "돈", "돈", "돈", "돈", "돈", "돈", "돈맛", "돌려주다", "돌려주다", "동의", "동의", "동의", "동의서", "동의서", "됀", "됀", "됀", "드리다", "드리다", "드리다", "드리다", "드리다", "드리다", "듣다", "듣다", "듣다", "듣다", "듣다", "듣다", "등기", "등기", "디스코드", "디스코드", "디스코드", "디지털", "디지털", "딜러", "딜러", "딥", "딥", "따다", "따다", "따다", "따다", "따다", "때리다", "때리다", "떨어지다", "떨어지다", "떨어지다", "뛰어내리다", "라이브스코어", "라이브스코어", "룰렛", "룰렛", "룰렛", "립니", "립니", "립니", "마약", "마약", "마약", "마약", "마약", "마약", "마음", "마음", "마음", "마음", "마음", "마이너스", "마이너스", "마이너스", "마이너스", "마이너스", "마이스터", "마이스터", "마작", "마작", "마진", "마진", "만들다", "만들다", "만들다", "만들다", "만들다", "만원", "만원", "만원", "만원", "만원", "만원", "만중", "만중", "만중", "만중", "만중", "많다", "많다", "많다", "많다", "많다", "많다", "많다", "많다", "말씀", "말씀", "말씀", "말씀", "말씀", "말씀", "말씀", "맛", "맛", "맛", "맛있다", "맛있다", "맴", "맴", "머릿속", "머릿속", "머릿속", "머릿속", "먹다", "먹다", "먹다", "먹다", "먹다", "먹다", "먹다", "먹다", "메꾸다", "메꾸다", "메신저", "메신저", "메이플", "메이플", "멘탈", "멘탈", "멘탈", "면허", "면허", "명령", "명령", "모르다", "모르다", "모르다", "모르다", "모르다", "모르다", "모르다", "모르다", "모르다", "모시다", "모시다", "모양", "모양", "목걸이", "목걸이", "목숨", "목표", "목표", "몸", "몸", "몸", "무리", "무리", "무리", "문자", "문자", "문자", "문자", "문제", "문제", "문제", "문제", "문제", "문제", "문제", "문제", "문제", "문제", "물다", "물다", "물다", "물다", "물다", "물다", "물다", "미성년자", "미성년자", "미성년자", "미성년자", "미성년자", "미성년자", "민사", "민사", "민사", "밉다", "밉다", "바카라", "바카라", "바카라", "바카라", "바카라", "박처", "박처", "반성", "반성", "반성", "반성", "반성", "반성", "방", "방", "방", "방관", "방관", "방금", "방금", "방법", "방법", "방법", "방법", "방법", "방법", "방법", "방법", "방학", "방학", "방학", "방학", "방학", "배", "배", "배", "배", "배", "배", "배", "배달", "배팅", "배팅", "배팅", "배팅", "배팅", "뱅크", "뱅크", "번개", "번개", "번개", "번호", "번호", "번호", "번호", "벌금", "벌금", "벌금", "벌금", "벌금", "벌다", "벌다", "벌다", "벌다", "벌다", "벌다", "벌리다", "벌리다", "범죄", "범죄", "범죄", "범죄", "범죄", "범죄", "법원", "법원", "법원", "법원", "변재", "변재", "변제", "변제", "변호사", "변호사", "변호사", "변호사", "변호사", "변호사", "보내다", "보내다", "보내다", "보내다", "보유", "보유", "보이스피싱", "보이스피싱", "보이스피싱", "보호", "보호", "보호관찰", "보호관찰", "보호자", "보호자", "보호자", "복", "복", "복구", "복구", "복구", "볼", "볼", "봉사", "봉사", "봉사", "부리다", "부리다", "부모", "부모", "부모", "부모", "부모", "부모", "부모", "부모", "부모", "부산", "부산", "부산", "부스타", "부스타", "부탁", "부탁", "부탁", "부탁", "부탁", "부탁", "부탁", "부탁", "분하다", "분하다", "불", "불", "불리", "불리", "불법", "불법", "불법", "불법", "불법", "불법", "불법", "불법원인급여", "불법원인급여", "불행", "불행", "비고", "비고", "비번", "비번", "비상금", "비상금", "빌리다", "빌리다", "빌리다", "빗", "빗", "빚", "빚", "빚", "빚", "빚다", "빚다", "빚다", "빚다", "빚다", "빛다", "빛다", "사건", "사건", "사건", "사건", "사건", "사고", "사고", "사고", "사고", "사고", "사귀다", "사귀다", "사기", "사기", "사기", "사기", "사기", "사기죄", "사기죄", "사기죄", "사기죄", "사다리", "사다리", "사다리", "사다리", "사다리", "사람", "사람", "사람", "사람", "사람", "사람", "사람", "사람", "사람", "사람", "사설", "사설", "사설", "사설", "사설", "사실", "사실", "사실", "사실", "사실", "사실", "사실", "사용", "사용", "사용", "사용", "사용", "사용", "사용", "사용", "사이버", "사이버", "사이버", "사이버", "사이트", "사이트", "사이트", "사이트", "사이트", "사이트", "사채", "사채", "사행성", "사행성", "사행성", "사회봉사", "사회봉사", "삭제", "삭제", "삭제", "삭제", "살다", "살다", "살다", "살다", "살다", "살다", "살다", "살다", "삼촌", "상담", "상담", "상담", "상담", "상담", "상대방", "상대방", "상습", "상습", "상습", "상습", "상위", "상위", "상태", "상태", "상태", "상태", "상태", "상태", "상태", "상품권", "상품권", "상환", "상환", "상황", "상황", "상황", "상황", "상황", "상황", "상황", "상황", "새끼", "새끼", "생각", "생각", "생각", "생각", "생각", "생각", "생각", "생각", "생각", "생각나다", "생각나다", "생각나다", "서류", "서류", "서버", "서버", "서버", "서버", "서부", "서부", "서울", "서울", "서울", "선도", "선도", "선도", "선물", "선물", "선물", "선생님", "선생님", "선생님", "선생님", "선생님", "선수", "선수", "선임", "선임", "선임", "섯다", "섯다", "섯다", "성격", "성격", "성격", "성격", "성인", "성인", "성인", "성인", "성인", "성인", "성인", "세금", "세금", "센터", "센터", "센터", "센터", "소년", "소년", "소년", "소년원", "소년원", "소년원", "소송", "소송", "소송", "속", "속", "속", "속", "손", "손", "손", "손", "손", "손", "손", "손", "손해", "손해", "손해", "송금", "송금", "송치", "송치", "수련", "수련", "수사", "수사", "수사", "수사관", "수사관", "수사대", "수사대", "수사대", "수업", "수업", "수업", "수업", "수위", "수위", "수위", "수익", "수익", "수익", "수중", "수중", "수학", "수학", "수학여행", "술", "술", "쉬다", "쉬다", "쉬다", "쉬다", "쉬다", "쉬다", "쉬다", "스케일", "스케일", "스트레스", "스트레스", "스트레스", "스포츠토토", "스포츠토토", "스포츠토토", "스포츠토토", "스포츠토토", "슬프다", "슬프다", "승인", "승인", "시작", "시작", "시작", "시작", "시작", "시작", "신", "신", "신경", "신경", "신경", "신경", "신고", "신고", "신고", "신고", "신고", "신고", "신원", "신원", "신한은행", "신한은행", "실력", "실력", "실천", "실천", "실형", "실형", "실형", "싫다", "싫다", "싫다", "싫다", "싫다", "싫다", "싫다", "심정", "심정", "아들", "아들", "아들", "아버님", "아버님", "아빠", "아빠", "아빠", "아빠", "아빠", "아빠", "아빠", "아빠", "아이템", "아이템", "아이패드", "아이패드", "악순환", "악순환", "애기", "애기", "앱", "앱", "앱", "앱", "앱", "약물", "약물", "양아치", "양아치", "양주", "양주", "얘기", "얘기", "얘기", "얘기", "얘기", "얘기", "억", "억", "억대", "억대", "엄두", "엄마", "엄마", "엄마", "엄마", "엄마", "엄마", "엄마", "여건", "여름", "여름", "여름", "여자", "여자", "여자", "연", "연", "연락", "연락", "연락", "연락", "연락", "연락", "연락", "연락", "영장", "영장", "영장", "영향", "영향", "영향", "예정", "예정", "예정", "예정", "예정", "오락", "오락", "오락", "오버", "오버", "오빠", "오빠", "오빠", "오토바이", "오토바이", "오토바이", "온라인", "온라인", "온라인", "온라인", "온라인", "온라인", "온라인", "온라인", "온라인", "온라인", "요구", "요구", "요구", "요구", "요구", "요번", "요번", "요번", "욕", "욕", "욕", "욕", "욕", "욕", "욕심", "욕심", "욕심", "용기", "용돈", "용돈", "용돈", "용돈", "용돈", "용돈", "우울증", "우울증", "우편", "우편", "우편", "우편", "운동", "운동", "운동", "울산", "울산", "울산", "웃다", "웃다", "웃다", "웃다", "워치", "워치", "원금", "원금", "원금", "원금", "원금", "원금", "위원회", "위원회", "위원회", "위원회", "유도", "유로", "유로", "유로", "유예", "유예", "유예", "유출", "유출", "유출", "유치장", "유치장", "유학", "유학", "은행", "은행", "은행", "은행", "은행", "의도", "의도", "의무", "의무", "의지", "의지", "의지", "이득", "이득", "이득", "이득", "이득", "이득", "이름", "이름", "이름", "이름", "이름", "이름", "이메일", "이메일", "이사", "이사", "이수", "이수", "이실직고", "이용자", "이용자", "이익", "이익", "이익", "이익", "이익", "이익", "이자", "이자", "이자", "이탈", "이탈", "인생", "인생", "인생", "인생", "인생", "인스타", "인스타", "인스타", "인스타", "인스타", "인스타", "인정", "인정", "인정", "인정", "인정", "인정", "인정", "인증", "인증", "인천", "인천", "일자", "일자", "일자", "일주일", "일지", "일지", "일진", "일진", "일탈", "일탈", "잃다", "잃다", "잃다", "잃다", "입금", "입금", "입금", "입금", "입금", "입금액", "입금액", "입금액", "입출", "입출", "입출금", "입출금", "입출금", "입출금", "자금", "자금", "자금", "자금", "자동", "자동", "자살", "자살", "자살", "자수", "자수", "자수", "자식", "자식", "자전거", "자전거", "자진", "자진", "자진", "자진", "자필", "자필", "작년", "작년", "작년", "작년", "작년", "작년", "작업", "작업", "작업대출", "잡히다", "잡히다", "잡히다", "잡히다", "장사", "장소", "장소", "장터", "장터", "재미있다", "재미있다", "재미있다", "재미있다", "재미있다", "재촉", "재촉", "재판", "재판", "재판", "잼", "잼", "저금", "저금", "저녁", "저녁", "저녁", "저녁", "저녁", "저녁", "저축", "저축", "저축", "적발", "적발", "적용", "적용", "적용", "적히다", "적히다", "적히다", "전말", "전말", "전문", "전문", "전문", "전학", "전학", "전화", "전화", "전화", "전화", "전화", "전화", "전화", "전화번호", "전화번호", "전화번호", "절제", "절제", "절제", "절제", "점유", "점유", "접다", "접다", "접다", "접다", "접다", "접다", "접다", "정보", "정보", "정보", "정시", "정시", "정신", "정신", "정신", "정신", "정신", "정신", "정신과", "정지", "정지", "제공", "제공", "제공", "제주도", "제주도", "조사", "조사", "조사", "조사", "조사", "조언", "조언", "조언", "조언", "조율", "조율", "조취", "조취", "조치", "조치", "조치", "조치", "조카", "조카", "조회", "조회", "조회", "조회", "조회", "조회", "조회", "종결", "종결", "종결", "종목", "종목", "좋다", "좋다", "좋다", "좋다", "좋다", "좋다", "좋다", "좋다", "주다", "주다", "주다", "주다", "주다", "주다", "주다", "주다", "주다", "주다", "주만", "주식", "주식", "주식", "주인", "주인", "주작", "주작", "죽다", "죽다", "죽다", "중독", "중독", "중독", "중독", "중독", "중독", "중학교", "중학교", "중학교", "중학교", "중학교", "중학교", "중학생", "중학생", "중학생", "중학생", "중학생", "중학생", "중학생", "중학생", "중학생", "중학생", "즉심", "즉심", "증거", "증거", "증거", "증거", "증상", "증상", "지금", "지금", "지금", "지금", "지금", "지금", "지금", "지내다", "지내다", "지내다", "지다", "지다", "지다", "지다", "지방", "지방", "지방", "지역", "지역", "지역", "지역", "지역", "지역", "지역", "지장", "지장", "지장", "지참", "지참", "직원", "직원", "진술서", "진술서", "진술서", "진학", "진학", "진학", "진행", "진행", "진행", "진행", "진행", "진행", "집안", "집안", "집안", "집행유예", "집행유예", "짜증", "짜증", "짜증", "쪽지", "차단", "차단", "차단", "차단", "차단", "차리다", "차리다", "차리다", "차리다", "차리다", "차리다", "차용증", "차용증", "참석", "참석", "찾다", "찾다", "찾다", "찾다", "찾다", "찾다", "채무", "채무", "처벌", "처벌", "처벌", "처벌", "처벌", "처벌", "처벌", "처분", "처분", "처분", "처분", "처분", "처분", "처분", "처음", "처음", "처음", "처음", "처음", "처음", "처음", "청법", "청법", "청소년", "청소년", "청소년", "청소년", "청소년", "청소년", "청소년", "청소년", "초등학교", "초등학교", "초등학교", "초등학생", "초등학생", "초등학생", "초범", "초범", "초범", "초범", "초심자", "초심자", "총판", "총판", "총판", "최종", "최종", "최종", "추심", "추심", "추천인", "추천인", "출금", "출금", "출금", "출금", "출금액", "출금액", "출석", "출석", "출석", "충동", "충동", "충동", "충전", "충전", "충전", "충전", "충전", "충전", "충청북도", "충청북도", "취업", "취업", "취업", "취업", "취업", "취업", "취직", "취직", "취직", "치다", "치다", "치다", "치다", "치다", "치다", "치료", "치료", "치료", "치료", "치료법", "치료법", "친구", "친구", "친구", "친구", "친구", "친구", "친구", "친구", "친구", "카카오톡", "카카오톡", "카카오톡", "카카오톡", "카카오톡", "카카오톡", "캡쳐", "캡쳐", "캡쳐", "컴퓨터", "컴퓨터", "코", "코", "코드", "코드", "코인", "코인", "키", "키", "탈퇴", "탈퇴", "탈퇴", "탈퇴", "택배", "택배", "탭", "탭", "털어놓다", "털어놓다", "털어놓다", "토토", "토토", "토토", "토토", "토토", "토토", "토토", "토토", "토토로", "토토로", "토토로", "토토로", "토토로", "톡", "톡", "통보", "통보", "통보", "통보", "통장", "통장", "통장", "통장", "통장", "통장", "통장", "통지서", "통지서", "통지서", "통지서", "특수", "특수", "팀", "팀", "팀", "팁", "팁", "파워", "파워", "판매", "판매", "판매", "판정", "판정", "팟", "팟", "패", "패", "패", "패다", "패다", "페메", "페메", "페북", "페북", "페이스북", "페이스북", "페이스북", "페이크", "페이크", "포상금", "포상금", "포인트", "포인트", "포인트", "포커", "포커", "폭행", "폭행", "폭행", "프로그램", "프로그램", "프로그램", "피다", "피다", "피싱", "피싱", "피파", "피파", "피폐", "피폐", "피해자", "피해자", "피해자", "필요", "필요", "필요", "필요", "필요", "필요", "필요", "하루", "하루", "하루", "하루", "하루", "하루", "하루", "하루하루", "하키", "하키", "학교", "학교", "학교", "학교", "학교", "학교", "학교", "학교", "학교", "학교폭력", "학교폭력", "학교폭력", "학교폭력", "학교폭력", "한국", "한국", "할머니", "할머니", "할머니", "합", "합", "합", "합리", "합리", "합리", "합의", "합의", "합의", "해결", "해결", "해결", "해결", "해결", "핸드폰", "핸드폰", "핸드폰", "핸드폰", "핸드폰", "행각", "행각", "행운", "행운", "헤어지다", "헤어지다", "현질", "현질", "현질", "협박", "협박", "협박", "협박", "형", "형", "형", "형", "형", "형벌", "형벌", "형벌", "형사", "형사", "형사", "형사", "형사", "호기심", "호기심", "호기심", "호기심", "호기심", "호기심", "홈페이지", "홈페이지", "홍보", "홍보", "화면", "화면", "화면", "화투", "화투", "화투", "확인", "확인", "확인", "확인", "확인", "확인", "확인", "환불", "환불", "환불", "환전", "환전", "환전", "환전", "활동", "활동", "활동", "회원", "회원", "회원", "회원", "횟수", "횟수", "횟수", "후반", "후반", "후반", "후반", "후회", "후회", "후회", "후회", "후회", "후회", "훈계", "훈계", "훈방", "훈방", "훈방", "휴대", "휴대", "휴대폰", "휴대폰", "휴대폰", "휴대폰", "휴대폰", "휴대폰", "휴대폰", "힘들다", "힘들다", "힘들다", "힘들다", "힘들다", "힘들다", "힘들다" ],
"Topic": [ 1, 2, 3, 5, 6, 8, 11, 2, 4, 5, 6, 1, 2, 5, 6, 7, 10, 1, 2, 7, 8, 10, 11, 2, 2, 3, 1, 2, 7, 2, 9, 2, 9, 2, 3, 9, 2, 6, 2, 3, 2, 6, 2, 2, 8, 9, 10, 11, 2, 3, 4, 5, 6, 7, 9, 10, 11, 1, 2, 3, 4, 6, 10, 11, 2, 4, 5, 6, 7, 8, 9, 10, 2, 7, 2, 8, 2, 6, 9, 1, 2, 4, 6, 7, 11, 2, 1, 2, 4, 8, 11, 2, 4, 2, 4, 6, 2, 9, 2, 8, 2, 3, 4, 5, 6, 8, 9, 10, 2, 8, 9, 2, 3, 6, 7, 8, 9, 2, 3, 5, 6, 11, 2, 3, 4, 5, 6, 7, 8, 9, 11, 2, 5, 8, 1, 2, 5, 6, 7, 9, 10, 1, 2, 3, 4, 5, 6, 7, 8, 9, 10, 2, 11, 2, 3, 10, 11, 2, 3, 7, 10, 2, 6, 9, 10, 1, 2, 4, 7, 9, 11, 2, 6, 2, 5, 2, 10, 2, 9, 2, 3, 7, 8, 2, 8, 2, 5, 6, 9, 2, 10, 2, 9, 2, 6, 8, 2, 6, 2, 10, 2, 3, 2, 5, 2, 6, 9, 10, 2, 6, 1, 2, 3, 4, 6, 7, 1, 2, 6, 8, 2, 5, 2, 11, 2, 3, 4, 8, 11, 1, 2, 4, 5, 6, 8, 9, 10, 2, 9, 2, 3, 5, 2, 3, 6, 9, 11, 2, 6, 7, 9, 2, 6, 9, 2, 10, 2, 3, 6, 8, 2, 3, 6, 2, 2, 2, 5, 2, 4, 5, 1, 2, 4, 1, 2, 4, 5, 7, 9, 1, 2, 4, 6, 7, 8, 9, 2, 3, 4, 6, 7, 8, 9, 10, 11, 1, 2, 3, 4, 5, 6, 1, 2, 2, 3, 7, 8, 2, 4, 7, 8, 10, 11, 2, 4, 5, 6, 7, 8, 9, 1, 2, 3, 7, 10, 2, 7, 2, 3, 5, 6, 8, 9, 10, 2, 3, 5, 8, 9, 1, 2, 4, 5, 6, 9, 2, 4, 2, 7, 11, 2, 3, 2, 7, 2, 7, 8, 11, 2, 5, 2, 3, 2, 6, 2, 6, 1, 2, 3, 4, 5, 6, 7, 9, 10, 11, 1, 2, 1, 2, 4, 7, 1, 2, 6, 10, 2, 6, 2, 3, 4, 5, 8, 9, 11, 2, 7, 2, 7, 2, 3, 10, 2, 5, 2, 8, 10, 2, 5, 2, 8, 2, 4, 2, 3, 2, 3, 10, 11, 2, 5, 2, 5, 2, 1, 2, 3, 4, 5, 6, 7, 8, 9, 10, 11, 2, 9, 11, 2, 3, 2, 4, 1, 2, 3, 5, 8, 10, 2, 1, 2, 3, 4, 5, 6, 11, 2, 2, 3, 2, 4, 9, 2, 9, 2, 4, 9, 1, 2, 5, 8, 9, 10, 1, 2, 6, 7, 8, 10, 2, 9, 2, 5, 8, 2, 10, 1, 2, 2, 10, 1, 2, 3, 4, 5, 2, 7, 2, 4, 6, 2, 2, 5, 2, 5, 11, 1, 2, 7, 1, 2, 5, 6, 8, 10, 1, 2, 4, 6, 7, 1, 2, 6, 7, 11, 2, 9, 2, 11, 2, 9, 2, 3, 4, 5, 7, 1, 2, 3, 4, 6, 7, 1, 2, 6, 7, 8, 1, 2, 4, 5, 6, 7, 8, 10, 2, 5, 6, 7, 8, 9, 10, 1, 2, 4, 2, 4, 2, 4, 1, 2, 6, 10, 1, 2, 3, 4, 5, 7, 9, 11, 1, 2, 2, 3, 2, 11, 1, 2, 4, 2, 10, 2, 10, 1, 2, 3, 4, 5, 6, 7, 8, 11, 2, 8, 2, 9, 2, 3, 2, 1, 2, 2, 4, 7, 2, 7, 9, 2, 5, 8, 10, 1, 2, 3, 4, 5, 6, 7, 8, 9, 11, 2, 3, 5, 6, 7, 8, 9, 2, 3, 5, 6, 8, 10, 2, 3, 10, 2, 7, 1, 2, 4, 6, 11, 2, 6, 2, 6, 7, 8, 9, 10, 1, 2, 5, 2, 3, 2, 4, 1, 2, 3, 4, 5, 7, 8, 10, 2, 4, 5, 7, 10, 1, 2, 3, 4, 6, 7, 11, 2, 2, 4, 5, 6, 10, 2, 5, 2, 6, 10, 2, 3, 5, 8, 2, 5, 6, 8, 9, 1, 2, 4, 5, 6, 7, 1, 2, 2, 3, 5, 6, 9, 10, 2, 9, 10, 11, 2, 10, 2, 10, 2, 3, 5, 6, 8, 10, 2, 3, 5, 8, 2, 9, 2, 5, 8, 2, 10, 2, 10, 2, 3, 8, 2, 11, 1, 2, 4, 2, 4, 2, 9, 10, 2, 4, 1, 2, 3, 4, 6, 7, 8, 9, 10, 2, 8, 11, 2, 11, 1, 2, 3, 4, 5, 6, 9, 10, 2, 4, 2, 4, 2, 9, 2, 3, 4, 5, 6, 8, 9, 2, 3, 2, 4, 2, 11, 2, 5, 2, 4, 2, 3, 7, 2, 11, 1, 2, 3, 4, 1, 2, 3, 7, 11, 1, 2, 2, 3, 5, 8, 10, 2, 3, 5, 7, 9, 2, 7, 2, 3, 5, 10, 11, 2, 3, 5, 10, 2, 4, 5, 6, 7, 1, 2, 3, 4, 5, 6, 7, 8, 9, 11, 2, 4, 5, 6, 9, 2, 3, 4, 6, 8, 9, 11, 2, 3, 5, 6, 8, 9, 10, 11, 2, 5, 6, 8, 1, 2, 4, 5, 6, 8, 2, 3, 2, 5, 9, 2, 9, 1, 2, 5, 9, 1, 2, 4, 5, 6, 7, 8, 9, 2, 1, 2, 6, 7, 8, 2, 3, 2, 3, 6, 10, 1, 2, 2, 3, 4, 6, 7, 9, 10, 2, 10, 2, 3, 1, 2, 3, 4, 5, 6, 8, 10, 2, 7, 1, 2, 3, 4, 5, 6, 7, 9, 11, 1, 2, 4, 2, 10, 2, 5, 6, 8, 2, 10, 2, 5, 8, 2, 8, 9, 2, 7, 11, 2, 3, 5, 7, 9, 2, 11, 2, 6, 10, 2, 4, 11, 1, 2, 4, 7, 1, 2, 3, 4, 6, 9, 10, 2, 11, 1, 2, 6, 8, 2, 9, 10, 2, 3, 10, 2, 3, 9, 1, 2, 4, 7, 1, 2, 3, 4, 5, 6, 7, 9, 1, 2, 4, 2, 5, 2, 10, 2, 11, 2, 8, 9, 2, 8, 2, 5, 8, 2, 6, 7, 8, 2, 6, 10, 2, 4, 5, 2, 4, 2, 7, 2, 2, 7, 1, 2, 3, 4, 7, 10, 11, 1, 2, 2, 4, 7, 1, 2, 7, 9, 11, 1, 2, 2, 5, 1, 2, 4, 5, 6, 7, 2, 7, 2, 6, 7, 11, 2, 3, 5, 8, 10, 11, 2, 9, 2, 9, 2, 4, 1, 2, 2, 8, 10, 1, 2, 3, 4, 7, 8, 11, 2, 4, 2, 3, 10, 2, 3, 2, 3, 4, 6, 7, 8, 9, 11, 2, 11, 2, 4, 1, 2, 2, 7, 1, 2, 5, 6, 11, 1, 2, 2, 7, 2, 11, 2, 3, 5, 7, 8, 11, 2, 9, 2, 6, 2, 1, 2, 3, 4, 7, 9, 11, 2, 2, 4, 9, 2, 3, 7, 2, 3, 1, 2, 3, 5, 6, 8, 9, 10, 2, 8, 10, 1, 2, 6, 2, 6, 8, 10, 11, 2, 4, 6, 2, 11, 2, 7, 10, 2, 7, 10, 1, 2, 3, 4, 5, 6, 7, 8, 9, 11, 2, 3, 5, 6, 8, 1, 2, 8, 1, 2, 4, 5, 7, 11, 1, 2, 4, 2, 1, 2, 3, 4, 6, 8, 2, 7, 2, 6, 8, 9, 1, 2, 7, 2, 8, 11, 1, 2, 4, 7, 2, 11, 1, 2, 3, 4, 5, 11, 2, 6, 8, 9, 2, 1, 2, 9, 2, 8, 9, 2, 5, 9, 2, 10, 2, 6, 2, 4, 5, 6, 9, 2, 3, 2, 3, 1, 2, 10, 1, 2, 3, 4, 5, 6, 2, 5, 8, 9, 10, 11, 2, 8, 2, 7, 2, 8, 2, 2, 8, 2, 4, 5, 8, 9, 11, 2, 3, 11, 2, 10, 1, 2, 4, 5, 7, 2, 3, 5, 6, 7, 8, 1, 2, 3, 4, 6, 8, 10, 2, 5, 2, 8, 2, 8, 9, 2, 1, 2, 2, 7, 2, 9, 1, 2, 4, 7, 2, 5, 6, 8, 10, 2, 6, 7, 2, 6, 2, 4, 6, 9, 2, 3, 5, 10, 2, 6, 1, 2, 7, 2, 6, 10, 2, 7, 2, 4, 2, 3, 6, 8, 2, 11, 1, 2, 3, 4, 6, 8, 2, 5, 2, 2, 3, 4, 6, 2, 2, 8, 2, 10, 1, 2, 3, 4, 11, 2, 3, 2, 3, 10, 2, 11, 1, 2, 2, 4, 5, 6, 10, 11, 1, 2, 9, 2, 6, 2, 6, 10, 2, 6, 9, 2, 3, 2, 10, 11, 2, 7, 1, 2, 3, 4, 5, 6, 8, 2, 5, 8, 1, 2, 9, 11, 2, 10, 2, 3, 4, 5, 6, 9, 11, 2, 5, 9, 2, 9, 1, 2, 3, 4, 7, 8, 2, 2, 5, 1, 2, 9, 1, 2, 2, 6, 8, 9, 10, 1, 2, 4, 9, 2, 8, 2, 6, 2, 6, 8, 9, 2, 7, 2, 3, 4, 5, 6, 9, 10, 2, 6, 8, 2, 4, 1, 2, 3, 4, 6, 7, 9, 10, 1, 2, 3, 4, 5, 7, 8, 9, 10, 11, 2, 2, 8, 11, 2, 3, 2, 3, 1, 2, 7, 1, 2, 3, 4, 7, 11, 1, 2, 3, 6, 7, 9, 1, 2, 3, 4, 5, 6, 7, 9, 10, 11, 2, 8, 2, 3, 5, 6, 1, 2, 1, 2, 3, 4, 6, 7, 10, 2, 7, 8, 1, 2, 5, 11, 2, 7, 8, 1, 2, 6, 7, 8, 9, 11, 2, 4, 6, 2, 8, 2, 5, 2, 8, 10, 2, 6, 9, 2, 3, 5, 8, 9, 11, 1, 2, 4, 2, 6, 2, 3, 4, 2, 2, 4, 5, 8, 9, 1, 2, 4, 8, 9, 10, 2, 3, 2, 8, 1, 2, 3, 4, 8, 11, 2, 3, 2, 3, 5, 6, 8, 9, 10, 2, 4, 6, 7, 8, 9, 10, 1, 2, 3, 4, 5, 6, 8, 2, 10, 1, 2, 3, 5, 6, 8, 9, 10, 2, 7, 9, 2, 5, 7, 2, 6, 8, 10, 2, 4, 2, 5, 7, 2, 4, 10, 2, 3, 2, 5, 2, 4, 5, 6, 2, 6, 2, 6, 8, 2, 4, 5, 1, 2, 3, 4, 5, 6, 2, 8, 1, 2, 5, 7, 9, 10, 2, 8, 9, 1, 2, 4, 7, 10, 11, 1, 2, 6, 7, 1, 2, 1, 2, 3, 4, 5, 6, 7, 8, 9, 2, 3, 5, 8, 10, 11, 2, 3, 5, 2, 11, 2, 11, 2, 5, 2, 11, 2, 7, 2, 4, 5, 6, 2, 11, 2, 11, 2, 7, 8, 1, 2, 3, 4, 5, 6, 8, 9, 1, 2, 3, 4, 6, 2, 5, 2, 6, 8, 9, 1, 2, 3, 4, 6, 9, 11, 2, 6, 9, 10, 2, 10, 2, 8, 11, 1, 2, 2, 4, 2, 3, 10, 2, 6, 1, 2, 2, 3, 11, 2, 7, 2, 5, 2, 5, 2, 5, 6, 2, 10, 2, 5, 2, 5, 6, 2, 11, 2, 3, 10, 2, 7, 8, 2, 7, 2, 8, 2, 11, 1, 2, 2, 3, 10, 1, 2, 3, 4, 8, 10, 11, 1, 2, 4, 5, 6, 8, 11, 2, 2, 4, 2, 3, 4, 5, 6, 7, 8, 9, 11, 2, 3, 6, 7, 10, 2, 11, 2, 4, 11, 2, 5, 6, 2, 4, 11, 2, 3, 10, 2, 3, 4, 9, 10, 2, 5, 7, 8, 11, 2, 10, 2, 4, 2, 7, 2, 3, 11, 2, 3, 5, 7, 2, 3, 5, 7, 10, 2, 5, 6, 2, 6, 8, 10, 11, 1, 2, 4, 5, 6, 7, 2, 8, 2, 5, 2, 6, 11, 2, 7, 11, 2, 3, 5, 6, 7, 8, 9, 1, 2, 10, 2, 4, 5, 6, 2, 3, 11, 2, 5, 6, 8, 2, 4, 6, 2, 4, 9, 11, 1, 2, 4, 6, 7, 10, 2, 11, 2, 6, 8, 2, 8, 2, 3, 5, 7, 8, 10, 11, 1, 2, 4, 6, 7, 8, 10 ],
"Freq": [ 0.04172149, 0.001264287, 0.5082436, 0.1732074, 0.1150502, 0.1517145, 0.007585725, 0.001341205, 0.02011808, 0.7577808, 0.2172752, 0.08238434, 0.1556149, 0.09153816, 0.01830763, 0.1281534, 0.5034599, 0.01297424, 0.2724589, 0.5741099, 0.06487118, 0.0551405, 0.009730677, 0.8767329, 0.02302159, 0.9208634, 0.03095697, 0.9054914, 0.03869621, 0.04811874, 0.8180186, 0.07054499, 0.7054499, 0.01768854, 0.8667384, 0.07075416, 0.07882619, 0.7094357, 0.6149045, 0.3840908, 0.05262708, 0.7894062, 0.9068659, 0.07436527, 0.1699778, 0.7197496, 0.01859132, 0.007967707, 0.0330277, 0.1146256, 0.1126828, 0.01942806, 0.2175943, 0.390504, 0.007771224, 0.08742627, 0.01748525, 0.1234429, 0.003336296, 0.3136118, 0.1734874, 0.04337185, 0.03669925, 0.3069392, 0.001573804, 0.1054449, 0.04564032, 0.6688667, 0.02203326, 0.01259043, 0.1306257, 0.01101663, 0.03630645, 0.8713549, 0.03102988, 0.8688365, 0.7581322, 0.06738953, 0.1179317, 0.1234976, 0.001436018, 0.1522179, 0.03015638, 0.1680141, 0.5227107, 0.8146348, 0.02707233, 0.2639552, 0.3722445, 0.05414465, 0.2639552, 0.04474592, 0.8054265, 0.008990096, 0.8720393, 0.09889106, 0.02462955, 0.9112932, 0.03542017, 0.850084, 0.0004696376, 0.04414593, 0.0112713, 0.05776542, 0.3531675, 0.3752404, 0.09157933, 0.0662189, 0.006553059, 0.8650038, 0.111402, 0.0006630687, 0.06829608, 0.1843331, 0.006630687, 0.6862761, 0.0530455, 0.002240813, 0.2106364, 0.5602033, 0.2173589, 0.006722439, 0.0005395144, 0.07661105, 0.04585873, 0.6242182, 0.06150465, 0.005395144, 0.1079029, 0.06959736, 0.008092716, 0.007994389, 0.903366, 0.06395512, 0.02392439, 0.2760507, 0.03496642, 0.03496642, 0.3441432, 0.2005968, 0.0828152, 0.1684487, 0.2656487, 0.0754952, 0.09767192, 0.06511461, 0.1642021, 0.02422138, 0.02768157, 0.08052822, 0.03066993, 0.06214037, 0.7456844, 0.003444749, 0.6269443, 0.2618009, 0.1033425, 0.01715002, 0.0857501, 0.0857501, 0.7717509, 0.008739789, 0.03495916, 0.8652392, 0.06117853, 0.09334111, 0.001261366, 0.2888529, 0.4944556, 0.04162509, 0.07820471, 0.03949898, 0.8294786, 0.1397709, 0.826978, 0.04677799, 0.7952259, 0.2664119, 0.6738654, 0.006600604, 0.03300302, 0.8646791, 0.07920725, 0.03102988, 0.8688365, 0.005819293, 0.8787132, 0.06401222, 0.04073505, 0.0556943, 0.7797202, 0.04811874, 0.8180186, 0.006320522, 0.2654619, 0.7078985, 0.06760731, 0.7436804, 0.0556943, 0.7797202, 0.6743164, 0.3030636, 0.03079406, 0.8930276, 0.02530195, 0.0506039, 0.7590585, 0.1012078, 0.05918399, 0.7693919, 0.543331, 0.003253479, 0.1594205, 0.04880218, 0.1431531, 0.09109741, 0.3239111, 0.009815487, 0.5987447, 0.03926195, 0.02146938, 0.9231835, 0.04544184, 0.8179531, 0.007731057, 0.688064, 0.04638634, 0.2164696, 0.02319317, 0.1349979, 0.0008709544, 0.1184498, 0.06183776, 0.515605, 0.02787054, 0.03222531, 0.1079983, 0.003770382, 0.9840698, 0.02077323, 0.8309292, 0.1038661, 0.4016493, 0.1905259, 0.3862012, 0.0102987, 0.007724024, 0.004708748, 0.4755835, 0.02354374, 0.485001, 0.01120101, 0.2128192, 0.7392666, 0.04677799, 0.7952259, 0.006351495, 0.03175747, 0.3112232, 0.6351495, 0.02460257,  0.86109, 0.04920515, 0.8767329, 0.9073683, 0.0238797, 0.9074287, 0.008487114, 0.8487114, 0.1273067, 0.7589835, 0.01851179, 0.1666061, 0.2078416, 0.07557877, 0.01889469, 0.03149115, 0.08817523, 0.5668407, 0.7797553, 0.0003129034, 0.1235969, 0.03817422, 0.03222905, 0.002503227, 0.02284195, 0.09369849, 0.1763736, 0.07440762, 0.2562929, 0.02755838, 0.09921016, 0.02755838, 0.1433036, 0.09921016, 0.2748975, 0.4427738, 0.05246136, 0.01888609, 0.06924899, 0.1363995, 0.8712898, 0.03485159, 0.006211037, 0.6397368, 0.08695452, 0.2484415, 0.0749123, 0.06609909, 0.5772654, 0.01762642, 0.01762642, 0.2379567, 0.1006843, 0.4401713, 0.02452567, 0.1303733, 0.09035775, 0.0309798, 0.1794247, 0.123063, 0.04269531, 0.2712408, 0.5048093, 0.05274127, 0.02166117, 0.909769, 0.001381839, 0.1022561, 0.07876484, 0.2003667, 0.2763679, 0.3330233, 0.005527357, 0.002729778, 0.5350364, 0.1692462, 0.2511396, 0.03821689, 0.1237895, 0.001509628, 0.4876099, 0.1856843, 0.1841747, 0.01509628, 0.05172078, 0.7758117, 0.018595, 0.8739648, 0.05578499, 0.02068937, 0.9310217, 0.0036458, 0.9843661, 0.009530619, 0.800572, 0.07624496, 0.08577557, 0.03079406, 0.8930276, 0.8865599, 0.06616119, 0.07882619, 0.7094357, 0.07882619, 0.7094357, 0.1366896, 0.002398063, 0.189447, 0.03597095, 0.01199032, 0.009592253, 0.4484378, 0.06474771, 0.04076708, 0.05755352, 0.8958718, 0.02714763, 0.1003737, 0.01115263, 0.7137685, 0.1561369, 0.8808488, 0.005992169, 0.07789819, 0.02396867, 0.03386681, 0.8466704, 0.03840832, 0.4544984, 0.09602079, 0.3168686, 0.06401386, 0.01280277, 0.009602079, 0.03105699, 0.8695956, 0.002792607, 0.9885829, 0.01613624, 0.1613624, 0.7745393, 0.02689966, 0.8876889, 0.01572057, 0.8803518, 0.06288227, 0.002505124, 0.9895241, 0.01558044, 0.9348267, 0.03942871, 0.828003, 0.0419261, 0.8385219, 0.5710566, 0.2527628, 0.1451046, 0.01404238, 0.02689966, 0.8876889, 0.03079406, 0.8930276, 0.8146348, 0.2789439, 0.1602801, 0.1274857, 0.08539001, 0.06266409, 0.1305062, 0.01294515, 0.07815032, 0.03595874, 0.02512317, 0.002445194, 0.02173588, 0.08694353, 0.8476995, 0.0419261, 0.8385219, 0.03942871, 0.828003, 0.4035272, 0.3691845, 0.09658896, 0.08156401, 0.008585686, 0.03648916, 0.9073683, 0.2075151, 0.1811807, 0.3233865, 0.2017621, 0.0854045, 0.0003241158, 0.0002430868, 0.8146348, 0.0147232, 0.9422851, 0.1410333, 0.07051666, 0.7051666, 0.04151926, 0.8303851, 0.03690169, 0.1107051, 0.7380338, 0.0668051, 0.7403095, 0.06407836, 0.03272086, 0.05453477, 0.03817434, 0.1125933, 0.003882528, 0.139771, 0.5979093, 0.1242409, 0.01553011, 0.01299751, 0.9488185, 0.03117744, 0.9301269, 0.02078496, 0.0556943, 0.7797202, 0.827228, 0.04866047, 0.04677799, 0.7952259, 0.4634935, 0.08183058, 0.01917904, 0.400842, 0.03324367, 0.02713377, 0.8954145, 0.02240061, 0.8064219, 0.08960243, 0.924663, 0.01124981, 0.9562336, 0.0224981, 0.1124905, 0.8099317, 0.8120721, 0.02194789, 0.1097395, 0.02550161, 0.006375401, 0.03187701, 0.2550161, 0.05100321, 0.6120385, 0.2873282, 0.1561566, 0.3575986, 0.05621638, 0.1389794, 0.7657368, 0.01701637, 0.03403275, 0.08508186, 0.05104912, 0.0572127, 0.8009778, 0.06214037, 0.7456844, 0.03258201, 0.8797143, 0.002433783, 0.03650674, 0.4186107, 0.3334283, 0.2044378, 0.2426293, 0.003676202, 0.03676202, 0.6212781, 0.05514303, 0.03676202, 0.09195876, 0.01021764, 0.5824055, 0.0510882, 0.2452234, 0.1419714, 0.09990578, 0.2923559, 0.0105164, 0.1020091, 0.2944591, 0.05468527, 0.004206559, 0.8426237, 0.0149225, 0.006963832, 0.01392766, 0.09948331, 0.01691216, 0.003979333, 0.1463783, 0.01125987, 0.8219707, 0.05172078, 0.7758117, 0.05172078, 0.7758117, 0.8450317, 0.01594399, 0.03188799, 0.06377598, 0.2259032, 0.1469064, 0.1025573, 0.167695,  0.09147,  0.21343, 0.005543636, 0.045735, 0.7572076, 0.1566636, 0.02972255, 0.8916764, 0.02955672, 0.8867015, 0.7518255, 0.007998144, 0.2159499, 0.03160075, 0.8848209, 0.02851664, 0.884016, 0.144225, 0.2467379, 0.08342426, 0.1343272, 0.1633136, 0.04029816, 0.1286713, 0.05373088, 0.004241912, 0.03542017, 0.850084, 0.0572127, 0.8009778, 0.01286786, 0.9522217, 0.8146348, 0.9174419, 0.0203876, 0.01618182, 0.7929094, 0.1618182, 0.0161074, 0.8375848, 0.1127518, 0.0009983888, 0.2915295, 0.6509495, 0.05491138, 0.0815211, 0.1778642, 0.2914997, 0.1272223, 0.03581988, 0.08399144, 0.0234682, 0.04446605, 0.1309278, 0.003705505, 0.002518177, 0.2719631, 0.2014542, 0.01762724, 0.1183543, 0.3424721, 0.04280901, 0.1435224, 0.2058058, 0.1665402, 0.3818239, 0.04332753, 0.0555134, 0.0104357, 0.9287773, 0.0417428, 0.03630645, 0.8713549, 0.1839098, 0.002043442, 0.3392114, 0.004086884, 0.4659048, 0.03949898, 0.8294786, 0.1080319, 0.4321276, 0.01385024, 0.1218822, 0.2105237, 0.1052619, 0.2251123, 0.004594128, 0.7580311, 0.02972255, 0.8916764, 0.02906665, 0.8719996, 0.3729021, 0.3542942, 0.1027156, 0.07443156, 0.06326683, 0.01042042, 0.01786358, 0.002977263, 0.06653891, 0.7374729, 0.05544909, 0.05544909, 0.07762873, 0.1610875, 0.004881438, 0.2391905, 0.07322157, 0.01952575, 0.2294276, 0.2635977, 0.8711297, 0.002368312, 0.5991831, 0.2226214, 0.1610452, 0.00947325, 0.00970925, 0.9612157, 0.0371676, 0.07433521, 0.7805197, 0.001183192, 0.04141172, 0.5963288, 0.3596904, 0.002522176, 0.07314309, 0.6910761, 0.1614192, 0.06809874, 0.3170373, 0.1717285, 0.3185051, 0.05577508, 0.03669413, 0.09687251, 0.1759607, 0.7624963, 0.002966129, 0.04449194, 0.04449194, 0.1245774, 0.1275436, 0.6495823, 0.00917922, 0.2478389, 0.6976207, 0.02753766, 0.0556943, 0.7797202, 0.03543284, 0.8503881, 0.004067804, 0.2196614, 0.02033902, 0.1708478, 0.1138985, 0.4596619, 0.002673827, 0.3155116, 0.5802206, 0.09625779, 0.03651168, 0.8397686, 0.006387729, 0.3641006, 0.613222, 0.01443181, 0.9380673, 0.009061222, 0.9604895, 0.007300013, 0.03650007, 0.9344017, 0.04544184, 0.8179531, 0.3990464, 0.001400163, 0.5950692, 0.01167698, 0.957512, 0.02265355, 0.7475672, 0.1585749, 0.04474592, 0.8054265, 0.1206055, 0.5935763, 0.03739387, 0.05136521, 0.0293809, 0.04889968, 0.1068396, 0.009656659, 0.002260069, 0.006459725, 0.3617446, 0.6136738, 0.05249516, 0.7874274, 0.2955321, 0.1147487, 0.2121769, 0.08552026, 0.1179963, 0.09634561, 0.03247605, 0.04438393, 0.04474592, 0.8054265, 0.03942871, 0.828003, 0.0572127, 0.8009778, 0.0003139633, 0.1676564, 0.00470945, 0.2954395, 0.3855469, 0.08163046, 0.06436248, 0.03478504, 0.8696259, 0.05172078, 0.7758117, 0.06214037, 0.7456844, 0.02146938, 0.9231835, 0.03185742, 0.8601502, 0.6111889, 0.3772771, 0.007545542, 0.06214037, 0.7456844, 0.05788655, 0.9072604, 0.03144798, 0.002504707, 0.08789372, 0.7617456, 0.04882985, 0.04882985, 0.02929791, 0.7888688, 0.06068221, 0.002957505, 0.1330877, 0.05619259, 0.2957505, 0.5057333, 0.2790471, 0.03135361, 0.07524866, 0.5863125, 0.02194753, 0.01663001, 0.9312805, 0.001416356, 0.00708178, 0.3795834, 0.5863714, 0.02124534, 0.00501819, 0.2709823, 0.1455275, 0.5670555, 0.003796793, 0.8466848, 0.07213906, 0.04935831, 0.01898396, 0.04913259, 0.0007018941, 0.2512781, 0.07861214, 0.3762153, 0.02807577, 0.1179182, 0.01684546, 0.05615153, 0.02526819, 0.1049621, 0.2155472, 0.1593175, 0.3786133, 0.1368256, 0.2332015, 0.167905, 0.004664029, 0.04974964, 0.2363108, 0.2674043, 0.03731223, 0.06789518, 0.04452143, 0.2303984, 0.4218405, 0.1380164, 0.004452143, 0.08459071, 0.006678214, 0.003905768, 0.01952884, 0.1093615, 0.859269, 0.0553186, 0.0003312491, 0.08711852, 0.3739803, 0.4206864, 0.06227483, 0.0259464, 0.908124, 0.01875902, 0.1875902, 0.7503607, 0.03258201, 0.8797143, 0.02203612, 0.00550903, 0.6996468, 0.2589244, 0.1851692, 0.2515886, 0.1730929, 0.0241525, 0.05333678, 0.2998936, 0.008050834, 0.004025417, 0.8711297, 0.7966821, 0.001278783, 0.1432237, 0.0306908, 0.02557567, 0.007073762, 0.9761791, 0.005111104, 0.1788887, 0.6491103, 0.1584442, 0.7888688, 0.06068221, 0.1617765, 0.1828075, 0.1714831, 0.1407456, 0.05338626, 0.03235531, 0.2556069, 0.0556943, 0.7797202, 0.03478504, 0.8696259, 0.01614737, 0.3577263, 0.2682947, 0.003726316, 0.1527789, 0.00248421, 0.06458947, 0.1316632, 0.02409058, 0.915442, 0.2997959, 0.1302936, 0.02081078, 0.307336, 0.01568349, 0.03106537, 0.1701055, 0.01990596, 0.004524083, 0.6722713, 0.004124364, 0.3134516, 0.0403226, 0.8467745, 0.01398931, 0.8673372, 0.02797862, 0.05595724, 0.0556943, 0.7797202, 0.04722399, 0.07870665, 0.8500318, 0.002874554, 0.2759572, 0.7128895, 0.03750696, 0.1875348, 0.6751254, 0.03769225, 0.2481407, 0.01570511, 0.3078201, 0.3863456, 0.04544184, 0.8179531, 0.01594766, 0.1754243, 0.7654876, 0.02173789, 0.3912821, 0.5217094, 0.1795331, 0.05129518, 0.02564759, 0.7181326, 0.2821948, 0.002391481, 0.3515477, 0.03587222, 0.1769696, 0.09565924, 0.0502211, 0.0400594, 0.8412475, 0.8981322, 0.002973948, 0.04460922, 0.04758316, 0.004696737, 0.01878695, 0.9675279, 0.00469072, 0.4831441, 0.4972163, 0.006831494, 0.9085888, 0.06831494, 0.1685161, 0.008024574, 0.6580151, 0.1524669, 0.2173422, 0.4218456, 0.03209695, 0.1879964, 0.01375583, 0.08895439, 0.03484811, 0.003668222, 0.2369147, 0.004834994, 0.7445891, 0.006666293, 0.9732787, 0.07346595, 0.8815914, 0.06214037, 0.7456844, 0.002136691, 0.9145038, 0.07905757, 0.01661446,  0.93041, 0.01052941, 0.2000588, 0.7581176, 0.01197145, 0.0239429, 0.7901159, 0.1436574, 0.003189893, 0.7783339, 0.207343, 0.02769252, 0.5446196, 0.4153878, 0.03185742, 0.8601502, 0.03105699, 0.8695956, 0.8711297, 0.06242021, 0.9206981, 0.03187592, 0.04781388, 0.0398449, 0.02390694, 0.7092393, 0.03187592, 0.09562777, 0.7888688, 0.06068221, 0.006203231, 0.2853486, 0.6947619, 0.02972504, 0.007431261, 0.03715631, 0.02972504, 0.8843201, 0.885108, 0.03052097, 0.02146938, 0.9231835, 0.3955957, 0.1380951, 0.3255098, 0.007787317, 0.07891148, 0.05347291, 0.02166117, 0.909769, 0.01533879, 0.03067758, 0.8589722, 0.04601637, 0.0004122434, 0.589508,  0.38957, 0.003297947, 0.009893841, 0.00618365, 0.02681083, 0.8847575, 0.0572127, 0.8009778, 0.05172078, 0.7758117, 0.827228, 0.04866047, 0.0310396, 0.1241584, 0.7449504, 0.08177911, 0.1952685, 0.008344807, 0.1118204, 0.5674469, 0.006675845, 0.02503442, 0.8157158, 0.1359526, 0.7072326, 0.1786309, 0.1020748, 0.03478504, 0.8696259, 0.3825373, 0.09413221, 0.006008439, 0.01902672, 0.4155837, 0.04406189, 0.007009845, 0.03004219, 0.0173951, 0.9393352, 0.04474592, 0.8054265, 0.8529018, 0.04061437, 0.03105699, 0.8695956, 0.07371379, 0.04914253, 0.7698996, 0.03276168, 0.04914253, 0.827228, 0.04866047, 0.01802559, 0.9373305, 0.06214037, 0.7456844, 0.001936996, 0.5791618, 0.04648791, 0.2886124, 0.06198387, 0.01743296, 0.0572127, 0.8009778, 0.07882619, 0.7094357, 0.8146348, 0.03270841, 0.4230288, 0.01817134, 0.1206577, 0.3423481, 0.05814829, 0.004361122, 0.8146348, 0.01295738, 0.8681446, 0.09070167, 0.026026, 0.1735066, 0.7894552, 0.02068937, 0.9310217, 0.02647707, 0.0283351, 0.2002038, 0.1463206, 0.1528238, 0.4008721, 0.02926412, 0.01439981, 0.02003965, 0.1603172, 0.7615066, 0.3396047, 0.01171051, 0.6206569, 0.07127405, 0.08909256, 0.6652244, 0.1247296, 0.03563702, 0.04145833, 0.124375, 0.7047916, 0.0400594, 0.8412475, 0.007768042, 0.9477011, 0.03107217, 0.01417946, 0.0708973, 0.8791265, 0.2947072, 0.08030169, 0.06343833, 0.002409051, 0.08351376, 0.2505413, 0.004015084, 0.144543, 0.04255989, 0.03372671, 0.002491933, 0.08721765, 0.2716207, 0.04734673, 0.5880962, 0.7373068, 0.0163846, 0.1966152, 0.2698747, 0.04626423, 0.04626423, 0.1118052, 0.4857744, 0.03469817, 0.08272771, 0.07636404, 0.8272771, 0.9681078, 0.5026911, 0.1146488, 0.02939714, 0.3370872, 0.001959809, 0.01175886, 0.01440022, 0.9504145, 0.006551706, 0.01310341, 0.7862047, 0.1768961, 0.04829414, 0.01207354, 0.9055152, 0.01116073, 0.4910721, 0.4687506, 0.053414, 0.0133535, 0.08012101, 0.8145636, 0.04544184, 0.8179531, 0.07056974, 0.00282279, 0.7198114, 0.1806585, 0.01411395, 0.008468369, 0.006393823, 0.01278765, 0.05115058, 0.9079228, 0.8711297, 0.8040447, 0.02772568, 0.1109027, 0.02381856, 0.1905485, 0.7145567, 0.009842862, 0.925229, 0.03937145, 0.0556943, 0.7797202, 0.06760731, 0.7436804, 0.05801556, 0.09214236, 0.3856328, 0.160396, 0.2934905, 0.0419261, 0.8385219, 0.03478504, 0.8696259, 0.8426754, 0.01138751, 0.1252626, 0.09667986, 0.004603803, 0.2255863, 0.6123058, 0.02301901, 0.03222662, 0.002801413, 0.739573, 0.1680848, 0.06443249, 0.01120565, 0.008404238, 0.01779549, 0.9253654, 0.02166117, 0.909769, 0.03102988, 0.8688365, 0.8146348, 0.03102988, 0.8688365, 0.006433256, 0.03859953, 0.1543981, 0.3602623, 0.4052951, 0.01929977, 0.2587016, 0.7295757, 0.005583488, 0.04677799, 0.7952259, 0.1375206, 0.283819, 0.2735781, 0.03511163, 0.2662632, 0.00617709, 0.1853127, 0.6980112, 0.01235418, 0.0617709, 0.02470836, 0.03580412, 0.008951031, 0.04475516, 0.05370619, 0.06265722, 0.2506289, 0.5281108, 0.005199644, 0.9827326, 0.006407933, 0.9740058, 0.02208122, 0.1766497, 0.7286802, 0.8711297, 0.827228, 0.04866047, 0.01269768, 0.9523264, 0.04811874, 0.8180186, 0.5097016, 0.05060867, 0.4381645, 0.0009512908, 0.005998581, 0.3999054, 0.4718884, 0.1159726, 0.003999054, 0.08884995, 0.7256079, 0.1480832, 0.01531038, 0.933933, 0.001817159, 0.005451476, 0.8613332, 0.1272011, 0.005234655, 0.6700359, 0.02617328, 0.287906, 0.07882619, 0.7094357, 0.1118405, 0.7694623, 0.1073668, 0.002522992, 0.9713517, 0.01766094, 0.03630645, 0.8713549, 0.03942871, 0.828003, 0.007918096, 0.8551544, 0.05542667, 0.06334477, 0.06214037, 0.7456844, 0.08172766, 0.1567563, 0.07234908, 0.09780523, 0.2934157, 0.2947555, 0.01950103, 0.9165485, 0.8767329, 0.01233495, 0.06167475, 0.1850243, 0.7030922, 0.9270799, 0.03102988, 0.8688365, 0.03543284, 0.8503881, 0.3022607, 0.009159415, 0.09159415, 0.219826, 0.3572172, 0.0259464, 0.908124, 0.003410379, 0.0170519, 0.9685476, 0.06214037, 0.7456844, 0.8529018, 0.04061437, 0.01055411, 0.4116104, 0.1583117, 0.04221645, 0.04221645, 0.3166234, 0.8761019, 0.01653022, 0.06612089, 0.005396381, 0.9767449, 0.03109265, 0.6529457, 0.2176486, 0.03818197, 0.07636394, 0.7636394, 0.0419261, 0.8385219, 0.01716567, 0.4806388, 0.4634731, 0.01663001, 0.9312805, 0.03916771, 0.02504165, 0.05072539, 0.001926281, 0.2690372, 0.06099889, 0.5515583, 0.009776348, 0.9189767, 0.03910539, 0.7042238, 0.06402035, 0.1067006, 0.09603052, 0.04677799, 0.7952259, 0.003539231, 0.01769615, 0.5450415, 0.1167946, 0.07432384, 0.2229715, 0.01061769, 0.002003436, 0.3305669, 0.6631372, 0.04811874, 0.8180186, 0.4680113, 0.2061109, 0.01549706, 0.1270759, 0.1301753, 0.0495906, 0.8146348, 0.003873863, 0.9839612, 0.01485352, 0.003713381, 0.9691924, 0.7888688, 0.06068221, 0.0006226945, 0.275231, 0.6245625, 0.008717723, 0.089668, 0.4307561, 0.3663726, 0.153294, 0.04598819, 0.02486572, 0.8951659, 0.06760731, 0.7436804, 0.002928663, 0.06735926, 0.843455, 0.07907391, 0.02713377, 0.8954145, 0.006491819, 0.1298364, 0.01947546, 0.0324591, 0.08439365, 0.5582965, 0.1558037, 0.02362884, 0.04725767, 0.8506381, 0.04474592, 0.8054265, 0.1473906, 0.3376924, 0.00932852, 0.2120684, 0.02114465, 0.2263721, 0.03731408, 0.008706619, 0.06173759, 0.0100115, 0.4738777, 0.06340617, 0.2828249, 0.01585154, 0.0500575, 0.01168008, 0.005840042, 0.02502875, 0.8711297, 0.3764992, 0.0537856, 0.5244096, 0.02972255, 0.8916764, 0.03478504, 0.8696259, 0.2018007, 0.6932551, 0.1017702, 0.7653882, 0.02580478, 0.002303998, 0.1999871, 0.002303998, 0.002764798, 0.09635775, 0.1129712, 0.09968043, 0.06313094, 0.5116929, 0.1096485, 0.3641188, 0.1316648, 0.09759521, 0.05784734, 0.09511097, 0.09511097, 0.1323746, 0.009582075, 0.01100164, 0.005323375, 0.03542017, 0.850084, 0.004015268, 0.7669161, 0.2087939, 0.008030536, 0.904493, 0.02444576, 0.4026141, 0.08561921, 0.09581197, 0.1967203, 0.1294481, 0.05707947, 0.03159756, 0.01161677, 0.8131738, 0.1394012, 0.132296, 0.768577, 0.06299812, 0.01889943, 0.01758858, 0.08794289, 0.8442517, 0.04150854, 0.01037713, 0.1349028, 0.05188567, 0.2905598, 0.1452799, 0.311314, 0.01766576, 0.1059946, 0.8302906, 0.04125752, 0.8251505, 0.01950103, 0.9165485, 0.009347684, 0.8973776, 0.06543379, 0.01807084, 0.2710626, 0.6686211, 0.005414858, 0.2924023, 0.1299566, 0.3465509, 0.037904, 0.1786903, 0.07561141, 0.8724393, 0.03489757, 0.05918399, 0.7693919, 0.01839274, 0.0919637, 0.846066, 0.8711297, 0.006872428, 0.02061728, 0.8727983, 0.05497942, 0.02748971, 0.6791698, 0.2106684, 0.01886583, 0.03773166, 0.01257722, 0.03458735, 0.01286786, 0.9522217, 0.03102988, 0.8688365, 0.1868421, 0.003062986, 0.1378344, 0.434944, 0.1225194, 0.1102675, 0.02302159, 0.9208634, 0.0003421531, 0.09888226, 0.06295618, 0.6713045, 0.07527369, 0.02395072, 0.06671986, 0.004299903, 0.01289971, 0.09889777, 0.02149952, 0.1891957, 0.06019864, 0.6062863, 0.3846967, 0.195127, 0.05495667, 0.1864822, 0.1136183, 0.04939925, 0.01481978, 0.04677799, 0.7952259, 0.227073, 0.1186912, 0.09463577, 0.0311928, 0.3000324, 0.2101549, 0.01242425, 0.00555126, 0.01847595, 0.8683696, 0.0739038, 0.0119758, 0.119758, 0.8383061, 0.002565519, 0.6336832, 0.2257657, 0.133407, 0.05172078, 0.7758117, 0.009289352, 0.9196459, 0.04644676, 0.01962573, 0.1766315, 0.7457776, 0.0419261, 0.8385219, 0.03079406, 0.8930276, 0.003123446, 0.0468517, 0.3092212, 0.6309362, 0.07882619, 0.7094357, 0.00110931,  0.09651, 0.8996507, 0.02374232, 0.7834965, 0.1187116, 0.111513, 0.001186309, 0.01779463, 0.4792687, 0.2182808, 0.1696422, 0.03542017, 0.850084, 0.03287146, 0.008217864, 0.04108932, 0.08217864, 0.7642614, 0.05752505, 0.03186439, 0.1274575, 0.7328809, 0.1351151, 0.002370441, 0.07822455, 0.4764586, 0.2607485, 0.04266793, 0.9417181, 0.002242186, 0.02017967, 0.0313906, 0.8529018, 0.04061437, 0.08951871, 0.09947727, 0.4457534, 0.04697838, 0.05044223, 0.04373103, 0.1946247, 0.009958551, 0.01937588, 0.002467695, 0.1579325, 0.582376, 0.2368987, 0.00987078, 0.007403085, 0.009803885, 0.9215652, 0.04901942, 0.3716642, 0.5817353, 0.05249516, 0.7874274, 0.02146938, 0.9231835, 0.04544184, 0.8179531, 0.02713377, 0.8954145, 0.002601351, 0.07804054, 0.5384797, 0.3719932, 0.06214037, 0.7456844, 0.05249516, 0.7874274, 0.7971453, 0.07971453, 0.06377162, 0.1578331, 0.01938302, 0.07476307, 0.1993682, 0.2720545, 0.1626789, 0.008307008, 0.1052221, 0.2758126, 0.004521518, 0.02260759, 0.5606682, 0.1266025, 0.03079406, 0.8930276, 0.01396514, 0.1256863, 0.2234423, 0.6005011, 0.02136572, 0.3188423, 0.04108793, 0.2087267, 0.1249073, 0.2777544, 0.004930552, 0.01395046, 0.2929596, 0.5998696, 0.05580182, 0.0403226, 0.8467745, 0.007162844, 0.7162844, 0.2578624, 0.8529018, 0.04061437, 0.008868158, 0.9666293, 0.0118406, 0.05920302, 0.8998859, 0.07882619, 0.7094357, 0.885108, 0.03052097, 0.02877207, 0.2877207, 0.6042135, 0.03630645, 0.8713549, 0.02146938, 0.9231835, 0.03079406, 0.8930276, 0.007835484, 0.8854097, 0.08619033, 0.04677799, 0.7952259, 0.02146938, 0.9231835, 0.020541, 0.8832631, 0.041082, 0.02190083, 0.919835, 0.007990247, 0.6711808, 0.3036294, 0.01160918, 0.1625285, 0.7894243, 0.007694337, 0.9694864, 0.02486572, 0.8951659, 0.0400594, 0.8412475, 0.827228, 0.04866047, 0.005371171, 0.1342793, 0.848645, 0.2529315, 0.002941064, 0.3323403, 0.05293916, 0.05882129, 0.1735228, 0.1235247, 0.4053693, 0.1489112, 0.3371183, 0.01034105, 0.02688674, 0.04136421, 0.02481853, 0.9447484, 0.03942871, 0.828003, 0.0006916084, 0.1528454, 0.09405874, 0.04564615, 0.06431958, 0.3091489, 0.06916084, 0.2081741, 0.05532867, 0.004766377, 0.2573844, 0.05243015, 0.2001878, 0.4766377, 0.02955672, 0.8867015, 0.790765, 0.1166702, 0.03889008, 0.02436923, 0.2436923, 0.6823383, 0.02157736, 0.7767849, 0.1294642, 0.00596501, 0.3221105, 0.6561511, 0.406145, 0.2371281, 0.2219923, 0.01009056, 0.1210867, 0.005830336, 0.2507044, 0.2740258, 0.2332134, 0.2273831, 0.0403226, 0.8467745, 0.04474592, 0.8054265, 0.01663001, 0.9312805, 0.02239977, 0.1119989, 0.8063918, 0.002155897, 0.7179136, 0.2026543, 0.07114459, 0.05735861, 0.866115, 0.02179627, 0.01606041, 0.03556234, 0.02134026, 0.1067013, 0.8109299, 0.003316517, 0.2520553, 0.384716, 0.3416013, 0.009949552, 0.2647837, 0.024255, 0.1596787, 0.1718062, 0.3577612, 0.0202125, 0.02760791, 0.883453, 0.01529438, 0.9482516, 0.03330573, 0.06661146, 0.7993375, 0.03750696, 0.1875348, 0.6751254, 0.09206579, 0.02707817, 0.1272674, 0.005415635, 0.03790944, 0.6932013, 0.01083127, 0.06703199, 0.016758, 0.8714158, 0.002536148, 0.2460064, 0.7405553, 0.005072297, 0.03717106, 0.1858553, 0.669079, 0.004054765, 0.7663505, 0.1905739, 0.03243812, 0.03285573, 0.0985672, 0.7556819, 0.01140597, 0.2737433, 0.3421791, 0.3421791, 0.08132391, 0.3704756, 0.1102391, 0.3397532, 0.05060155, 0.04337275, 0.05249516, 0.7874274, 0.002571555, 0.1568648, 0.8331837, 0.02486572, 0.8951659, 0.003249168, 0.1299667, 0.3541593, 0.1689567, 0.01299667, 0.01299667, 0.3184185, 0.1699795, 0.4486534, 0.1711358, 0.01271956, 0.1722922, 0.01850117, 0.004625293 ] 
},
"R":       30,
"lambda.step":     0.01,
"plot.opts": {
 "xlab": "PC1",
"ylab": "PC2" 
},
"topic.order": [ 6, 11, 10, 3, 9, 1, 8, 7, 5, 4, 2 ] 
}